[{"0": [{"bank_0": {"assets": {"interbank_loans": 0.0, "loans": 5923809002.0, "reserves": 453849882.84000015, "bank_notes": 0.0, "open_market_operations": 23941926894.16, "ach_payee_bank_0": 0.0}, "liabilities": {"deposits": 22692494142.0, "receivables": 0.0, "loans_central_bank": 0.0, "ach_payer_bank_0": 0.0, "loans_interbank_bank_0": 0.0, "equity": 7627091637.0}}}, {"bank_1": {"assets": {"interbank_loans": 0.0, "loans": 3551182367.0, "reserves": 334277602.08000183, "bank_notes": 0.0, "open_market_operations": 19056766637.92, "ach_payee_bank_1": 0.0}, "liabilities": {"deposits": 16713880104.0, "receivables": 0.0, "loans_central_bank": 0.0, "ach_payer_bank_1": 0.0, "loans_interbank_bank_1": 0.0, "equity": 6228346503.0}}}, {"bank_2": {"assets": {"interbank_loans": 0.0, "loans": 9032447152.0, "reserves": 469968138.4399986, "bank_notes": 0.0, "open_market_operations": 21581448179.56, "ach_payee_bank_2": 0.0}, "liabilities": {"deposits": 23498406922.0, "receivables": 0.0, "loans_central_bank": 0.0, "ach_payer_bank_2": 0.0, "loans_interbank_bank_2": 0.0, "equity": 7585456548.0}}}, {"bank_3": {"assets": {"interbank_loans": 0.0, "loans": 7178366825.0, "reserves": 381616334.7399998, "bank_notes": 0.0, "open_market_operations": 15765744309.26, "ach_payee_bank_3": 0.0}, "liabilities": {"deposits": 19080816737.0, "receivables": 0.0, "loans_central_bank": 0.0, "ach_payer_bank_3": 0.0, "loans_interbank_bank_3": 0.0, "equity": 4244910732.0}}}]},{"1": [{"bank_0": {"assets": {"interbank_loans": 0.0, "loans": 6052480282.437183, "reserves": 459469674.65499693, "bank_notes": 0.0, "open_market_operations": 24668117609.54353, "ach_payee_bank_0": 0.0}, "liabilities": {"deposits": 22973483732.749847, "receivables": 0.0, "loans_central_bank": 0.0, "ach_payer_bank_0": 0.0, "loans_interbank_bank_0": 0.0, "equity": 8206583833.885864}}}, {"bank_1": {"assets": {"interbank_loans": 0.0, "loans": 3628317734.138537, "reserves": 330180862.6758894, "bank_notes": 0.0, "open_market_operations": 19226676652.792393, "ach_payee_bank_1": 0.0}, "liabilities": {"deposits": 16509043133.794468, "receivables": 0.0, "loans_central_bank": 0.0, "ach_payer_bank_1": 0.0, "loans_interbank_bank_1": 0.0, "equity": 6676132115.812351}}}, {"bank_2": {"assets": {"interbank_loans": 0.0, "loans": 9228641279.821585, "reserves": 475206452.6791883, "bank_notes": 0.0, "open_market_operations": 22217832020.014606, "ach_payee_bank_2": 0.0}, "liabilities": {"deposits": 23760322633.959415, "receivables": 0.0, "loans_central_bank": 0.0, "ach_payer_bank_2": 0.0, "loans_interbank_bank_2": 0.0, "equity": 8161357118.555965}}}, {"bank_3": {"assets": {"interbank_loans": 0.0, "loans": 7334288403.583764, "reserves": 389223537.69850564, "bank_notes": 0.0, "open_market_operations": 16399103380.606287, "ach_payee_bank_3": 0.0}, "liabilities": {"deposits": 19461176884.92528, "receivables": 0.0, "loans_central_bank": 0.0, "ach_payer_bank_3": 0.0, "loans_interbank_bank_3": 0.0, "equity": 4661438436.963276}}}]},{"2": [{"bank_0": {"assets": {"interbank_loans": 0.0, "loans": 6183946436.646254, "reserves": 463934330.8877884, "bank_notes": 0.0, "open_market_operations": 25354949833.8229, "ach_payee_bank_0": 0.0}, "liabilities": {"deposits": 23196716544.38942, "receivables": 0.0, "loans_central_bank": 0.0, "ach_payer_bank_0": 0.0, "loans_interbank_bank_0": 0.0, "equity": 8806114056.967522}}}, {"bank_1": {"assets": {"interbank_loans": 0.0, "loans": 3707128561.5178337, "reserves": 324692325.7936182, "bank_notes": 0.0, "open_market_operations": 19334794113.831097, "ach_payee_bank_1": 0.0}, "liabilities": {"deposits": 16234616289.68091, "receivables": 0.0, "loans_central_bank": 0.0, "ach_payer_bank_1": 0.0, "loans_interbank_bank_1": 0.0, "equity": 7131998711.4616375}}}, {"bank_2": {"assets": {"interbank_loans": 0.0, "loans": 9429096947.748957, "reserves": 481684212.92247134, "bank_notes": 0.0, "open_market_operations": 22929922069.584084, "ach_payee_bank_2": 0.0}, "liabilities": {"deposits": 24084210646.123566, "receivables": 0.0, "loans_central_bank": 0.0, "ach_payer_bank_2": 0.0, "loans_interbank_bank_2": 0.0, "equity": 8756492584.131947}}}, {"bank_3": {"assets": {"interbank_loans": 0.0, "loans": 7493596760.700966, "reserves": 398264137.5059002, "bank_notes": 0.0, "open_market_operations": 17116552262.104391, "ach_payee_bank_3": 0.0}, "liabilities": {"deposits": 19913206875.29501, "receivables": 0.0, "loans_central_bank": 0.0, "ach_payer_bank_3": 0.0, "loans_interbank_bank_3": 0.0, "equity": 5095206285.016247}}}]},{"3": [{"bank_0": {"assets": {"interbank_loans": 0.0, "loans": 6358490090.249402, "reserves": 472218041.33380795, "bank_notes": 0.0, "open_market_operations": 26205375057.9126, "ach_payee_bank_0": 0.0}, "liabilities": {"deposits": 23610902066.690395, "receivables": 0.0, "loans_central_bank": 0.0, "ach_payer_bank_0": 0.0, "loans_interbank_bank_0": 0.0, "equity": 9425181122.805416}}}, {"bank_1": {"assets": {"interbank_loans": 0.0, "loans": 3787651241.8734484, "reserves": 320940422.781396, "bank_notes": 0.0, "open_market_operations": 19533345202.158455, "ach_payee_bank_1": 0.0}, "liabilities": {"deposits": 16047021139.0698, "receivables": 0.0, "loans_central_bank": 0.0, "ach_payer_bank_1": 0.0, "loans_interbank_bank_1": 0.0, "equity": 7594915727.743502}}}, {"bank_2": {"assets": {"interbank_loans": 0.0, "loans": 9663021923.50638, "reserves": 490069059.0720689, "bank_notes": 0.0, "open_market_operations": 23722828739.156174, "ach_payee_bank_2": 0.0}, "liabilities": {"deposits": 24503452953.603447, "receivables": 0.0, "loans_central_bank": 0.0, "ach_payer_bank_2": 0.0, "loans_interbank_bank_2": 0.0, "equity": 9372466768.131176}}}, {"bank_3": {"assets": {"interbank_loans": 0.0, "loans": 7785687746.32846, "reserves": 403942164.5733389, "bank_notes": 0.0, "open_market_operations": 17555419930.16262, "ach_payee_bank_3": 0.0}, "liabilities": {"deposits": 20197108228.666946, "receivables": 0.0, "loans_central_bank": 0.0, "ach_payer_bank_3": 0.0, "loans_interbank_bank_3": 0.0, "equity": 5547941612.397472}}}]},{"4": [{"bank_0": {"assets": {"interbank_loans": 0.0, "loans": 6562057431.177473, "reserves": 475782937.53804886, "bank_notes": 0.0, "open_market_operations": 26818793085.534954, "ach_payee_bank_0": 0.0}, "liabilities": {"deposits": 23789146876.902443, "receivables": 0.0, "loans_central_bank": 0.0, "ach_payer_bank_0": 0.0, "loans_interbank_bank_0": 0.0, "equity": 10067486577.348034}}}, {"bank_1": {"assets": {"interbank_loans": 0.0, "loans": 3869922958.4289284, "reserves": 316820045.5216268, "bank_notes": 0.0, "open_market_operations": 19720872672.27484, "ach_payee_bank_1": 0.0}, "liabilities": {"deposits": 15841002276.081339, "receivables": 0.0, "loans_central_bank": 0.0, "ach_payer_bank_1": 0.0, "loans_interbank_bank_1": 0.0, "equity": 8066613400.144056}}}, {"bank_2": {"assets": {"interbank_loans": 0.0, "loans": 10040314340.637344, "reserves": 503003476.6415761, "bank_notes": 0.0, "open_market_operations": 24618220082.663734, "ach_payee_bank_2": 0.0}, "liabilities": {"deposits": 25150173832.078804, "receivables": 0.0, "loans_central_bank": 0.0, "ach_payer_bank_2": 0.0, "loans_interbank_bank_2": 0.0, "equity": 10011364067.863853}}}, {"bank_3": {"assets": {"interbank_loans": 0.0, "loans": 8092554573.442626, "reserves": 413759853.09400654, "bank_notes": 0.0, "open_market_operations": 18198120718.397385, "ach_payee_bank_3": 0.0}, "liabilities": {"deposits": 20687992654.700325, "receivables": 0.0, "loans_central_bank": 0.0, "ach_payer_bank_3": 0.0, "loans_interbank_bank_3": 0.0, "equity": 6016442490.233692}}}]},{"5": [{"bank_0": {"assets": {"interbank_loans": 0.0, "loans": 6739742194.681439, "reserves": 481565244.43807906, "bank_notes": 0.0, "open_market_operations": 27586251875.169743, "ach_payee_bank_0": 0.0}, "liabilities": {"deposits": 24078262221.903954, "receivables": 0.0, "loans_central_bank": 0.0, "ach_payer_bank_0": 0.0, "loans_interbank_bank_0": 0.0, "equity": 10729297092.385307}}}, {"bank_1": {"assets": {"interbank_loans": 0.0, "loans": 4000601466.9874306, "reserves": 311558489.3518224, "bank_notes": 0.0, "open_market_operations": 19812756545.717087, "ach_payee_bank_1": 0.0}, "liabilities": {"deposits": 15577924467.59112, "receivables": 0.0, "loans_central_bank": 0.0, "ach_payer_bank_1": 0.0, "loans_interbank_bank_1": 0.0, "equity": 8546992034.4652195}}}, {"bank_2": {"assets": {"interbank_loans": 0.0, "loans": 10479688934.29324, "reserves": 512702403.2734224, "bank_notes": 0.0, "open_market_operations": 25319814991.300648, "ach_payee_bank_2": 0.0}, "liabilities": {"deposits": 25635120163.67112, "receivables": 0.0, "loans_central_bank": 0.0, "ach_payer_bank_2": 0.0, "loans_interbank_bank_2": 0.0, "equity": 10677086165.19619}}}, {"bank_3": {"assets": {"interbank_loans": 0.0, "loans": 8301031447.11861, "reserves": 425234248.0825016, "bank_notes": 0.0, "open_market_operations": 19040193889.145992, "ach_payee_bank_3": 0.0}, "liabilities": {"deposits": 21261712404.12508, "receivables": 0.0, "loans_central_bank": 0.0, "ach_payer_bank_3": 0.0, "loans_interbank_bank_3": 0.0, "equity": 6504747180.222027}}}]},{"6": [{"bank_0": {"assets": {"interbank_loans": 0.0, "loans": 6988383149.684948, "reserves": 489674761.74321693, "bank_notes": 0.0, "open_market_operations": 28418939051.070618, "ach_payee_bank_0": 0.0}, "liabilities": {"deposits": 24483738087.160847, "receivables": 0.0, "loans_central_bank": 0.0, "ach_payer_bank_0": 0.0, "loans_interbank_bank_0": 0.0, "equity": 11413258875.337933}}}, {"bank_1": {"assets": {"interbank_loans": 0.0, "loans": 4170169297.331534, "reserves": 309796848.5731635, "bank_notes": 0.0, "open_market_operations": 20044884038.2405, "ach_payee_bank_1": 0.0}, "liabilities": {"deposits": 15489842428.658176, "receivables": 0.0, "loans_central_bank": 0.0, "ach_payer_bank_1": 0.0, "loans_interbank_bank_1": 0.0, "equity": 9035007755.487022}}}, {"bank_2": {"assets": {"interbank_loans": 0.0, "loans": 10983669144.369186, "reserves": 525834079.88814425, "bank_notes": 0.0, "open_market_operations": 26149341197.216103, "ach_payee_bank_2": 0.0}, "liabilities": {"deposits": 26291703994.40721, "receivables": 0.0, "loans_central_bank": 0.0, "ach_payer_bank_2": 0.0, "loans_interbank_bank_2": 0.0, "equity": 11367140427.066223}}}, {"bank_3": {"assets": {"interbank_loans": 0.0, "loans": 8692974620.536343, "reserves": 434381818.5092223, "bank_notes": 0.0, "open_market_operations": 19607137197.944736, "ach_payee_bank_3": 0.0}, "liabilities": {"deposits": 21719090925.461117, "receivables": 0.0, "loans_central_bank": 0.0, "ach_payer_bank_3": 0.0, "loans_interbank_bank_3": 0.0, "equity": 7015402711.529186}}}]},{"7": [{"bank_0": {"assets": {"interbank_loans": 0.0, "loans": 7346286968.771831, "reserves": 498531131.6319184, "bank_notes": 0.0, "open_market_operations": 29203401992.200718, "ach_payee_bank_0": 0.0}, "liabilities": {"deposits": 24926556581.595917, "receivables": 0.0, "loans_central_bank": 0.0, "ach_payer_bank_0": 0.0, "loans_interbank_bank_0": 0.0, "equity": 12121663511.008553}}}, {"bank_1": {"assets": {"interbank_loans": 0.0, "loans": 4428527556.712786, "reserves": 306323225.68151194, "bank_notes": 0.0, "open_market_operations": 20115087874.572304, "ach_payee_bank_1": 0.0}, "liabilities": {"deposits": 15316161284.075596, "receivables": 0.0, "loans_central_bank": 0.0, "ach_payer_bank_1": 0.0, "loans_interbank_bank_1": 0.0, "equity": 9533777372.891006}}}, {"bank_2": {"assets": {"interbank_loans": 0.0, "loans": 11407451813.639774, "reserves": 539379250.5805008, "bank_notes": 0.0, "open_market_operations": 27107029041.705757, "ach_payee_bank_2": 0.0}, "liabilities": {"deposits": 26968962529.025043, "receivables": 0.0, "loans_central_bank": 0.0, "ach_payer_bank_2": 0.0, "loans_interbank_bank_2": 0.0, "equity": 12084897576.90099}}}, {"bank_3": {"assets": {"interbank_loans": 0.0, "loans": 8997845421.74075, "reserves": 444376661.2275286, "bank_notes": 0.0, "open_market_operations": 20322558883.28641, "ach_payee_bank_3": 0.0}, "liabilities": {"deposits": 22218833061.376427, "receivables": 0.0, "loans_central_bank": 0.0, "ach_payer_bank_3": 0.0, "loans_interbank_bank_3": 0.0, "equity": 7545947904.878262}}}]},{"8": [{"bank_0": {"assets": {"interbank_loans": 0.0, "loans": 7723811036.740142, "reserves": 508899971.9415384, "bank_notes": 0.0, "open_market_operations": 30067536081.736027, "ach_payee_bank_0": 0.0}, "liabilities": {"deposits": 25444998597.07692, "receivables": 0.0, "loans_central_bank": 0.0, "ach_payer_bank_0": 0.0, "loans_interbank_bank_0": 0.0, "equity": 12855248493.34079}}}, {"bank_1": {"assets": {"interbank_loans": 0.0, "loans": 4731904388.033505, "reserves": 305416466.3628209, "bank_notes": 0.0, "open_market_operations": 20275088211.847668, "ach_payee_bank_1": 0.0}, "liabilities": {"deposits": 15270823318.141047, "receivables": 0.0, "loans_central_bank": 0.0, "ach_payer_bank_1": 0.0, "loans_interbank_bank_1": 0.0, "equity": 10041585748.10295}}}, {"bank_2": {"assets": {"interbank_loans": 0.0, "loans": 11882939825.239782, "reserves": 553652056.5971946, "bank_notes": 0.0, "open_market_operations": 28077923127.79927, "ach_payee_bank_2": 0.0}, "liabilities": {"deposits": 27682602829.85973, "receivables": 0.0, "loans_central_bank": 0.0, "ach_payer_bank_2": 0.0, "loans_interbank_bank_2": 0.0, "equity": 12831912179.776516}}}, {"bank_3": {"assets": {"interbank_loans": 0.0, "loans": 9464461619.433094, "reserves": 454795512.7435874, "bank_notes": 0.0, "open_market_operations": 20918667746.35183, "ach_payee_bank_3": 0.0}, "liabilities": {"deposits": 22739775637.179367, "receivables": 0.0, "loans_central_bank": 0.0, "ach_payer_bank_3": 0.0, "loans_interbank_bank_3": 0.0, "equity": 8098149241.349144}}}]},{"9": [{"bank_0": {"assets": {"interbank_loans": 0.0, "loans": 8148706947.80391, "reserves": 515382780.5687656, "bank_notes": 0.0, "open_market_operations": 30720988519.076214, "ach_payee_bank_0": 0.0}, "liabilities": {"deposits": 25769139028.43828, "receivables": 0.0, "loans_central_bank": 0.0, "ach_payer_bank_0": 0.0, "loans_interbank_bank_0": 0.0, "equity": 13615939219.010612}}}, {"bank_1": {"assets": {"interbank_loans": 0.0, "loans": 5145199250.47267, "reserves": 304124425.90230703, "bank_notes": 0.0, "open_market_operations": 20323595521.985634, "ach_payee_bank_1": 0.0}, "liabilities": {"deposits": 15206221295.115349, "receivables": 0.0, "loans_central_bank": 0.0, "ach_payer_bank_1": 0.0, "loans_interbank_bank_1": 5975167.798051953, "equity": 10560722735.44721}}}, {"bank_2": {"assets": {"interbank_loans": 0.0, "loans": 12340460215.943604, "reserves": 570283954.5872176, "bank_notes": 0.0, "open_market_operations": 29212800435.568863, "ach_payee_bank_2": 0.0}, "liabilities": {"deposits": 28514197729.360878, "receivables": 0.0, "loans_central_bank": 0.0, "ach_payer_bank_2": 0.0, "loans_interbank_bank_2": 0.0, "equity": 13609346876.738808}}}, {"bank_3": {"assets": {"interbank_loans": 5975167.798051953, "loans": 9943274473.725204, "reserves": 469751180.69359607, "bank_notes": 0.0, "open_market_operations": 21740654841.854046, "ach_payee_bank_3": 0.0}, "liabilities": {"deposits": 23487559034.679802, "receivables": 0.0, "loans_central_bank": 0.0, "ach_payer_bank_3": 0.0, "loans_interbank_bank_3": 0.0, "equity": 8672096629.391098}}}]},{"10": [{"bank_0": {"assets": {"interbank_loans": 0.0, "loans": 8467680932.432635, "reserves": 520483489.1037834, "bank_notes": 0.0, "open_market_operations": 31436760408.87489, "ach_payee_bank_0": 0.0}, "liabilities": {"deposits": 26024174455.18917, "receivables": 0.0, "loans_central_bank": 0.0, "ach_payer_bank_0": 0.0, "loans_interbank_bank_0": 0.0, "equity": 14400750375.222137}}}, {"bank_1": {"assets": {"interbank_loans": 0.0, "loans": 5558236220.543534, "reserves": 307660173.8467149, "bank_notes": 0.0, "open_market_operations": 20607831574.678436, "ach_payee_bank_1": 0.0}, "liabilities": {"deposits": 15383008692.335745, "receivables": 0.0, "loans_central_bank": 0.0, "ach_payer_bank_1": 0.0, "loans_interbank_bank_1": 0.0, "equity": 11090719276.732943}}}, {"bank_2": {"assets": {"interbank_loans": 0.0, "loans": 12849171435.491816, "reserves": 583706284.0806135, "bank_notes": 0.0, "open_market_operations": 30172663995.99803, "ach_payee_bank_2": 0.0}, "liabilities": {"deposits": 29185314204.030674, "receivables": 0.0, "loans_central_bank": 0.0, "ach_payer_bank_2": 0.0, "loans_interbank_bank_2": 0.0, "equity": 14420227511.539791}}}, {"bank_3": {"assets": {"interbank_loans": 0.0, "loans": 10538297797.848928, "reserves": 485246551.8185846, "bank_notes": 0.0, "open_market_operations": 22510979740.093697, "ach_payee_bank_3": 0.0}, "liabilities": {"deposits": 24262327590.92923, "receivables": 0.0, "loans_central_bank": 0.0, "ach_payer_bank_3": 0.0, "loans_interbank_bank_3": 0.0, "equity": 9272196498.831978}}}]},{"11": [{"bank_0": {"assets": {"interbank_loans": 0.0, "loans": 9012544919.463297, "reserves": 532416944.6931868, "bank_notes": 0.0, "open_market_operations": 32285563214.87795, "ach_payee_bank_0": 0.0}, "liabilities": {"deposits": 26620847234.65934, "receivables": 0.0, "loans_central_bank": 0.0, "ach_payer_bank_0": 0.0, "loans_interbank_bank_0": 0.0, "equity": 15209677844.375092}}}, {"bank_1": {"assets": {"interbank_loans": 0.0, "loans": 5956379384.081512, "reserves": 309216448.05749345, "bank_notes": 0.0, "open_market_operations": 20831077656.283405, "ach_payee_bank_1": 0.0}, "liabilities": {"deposits": 15460822402.874672, "receivables": 0.0, "loans_central_bank": 0.0, "ach_payer_bank_1": 0.0, "loans_interbank_bank_1": 0.0, "equity": 11635851085.547737}}}, {"bank_2": {"assets": {"interbank_loans": 0.0, "loans": 13538829549.446394, "reserves": 598901629.7192583, "bank_notes": 0.0, "open_market_operations": 31069673503.24254, "ach_payee_bank_2": 0.0}, "liabilities": {"deposits": 29945081485.962917, "receivables": 0.0, "loans_central_bank": 0.0, "ach_payer_bank_2": 0.0, "loans_interbank_bank_2": 0.0, "equity": 15262323196.44527}}}, {"bank_3": {"assets": {"interbank_loans": 0.0, "loans": 10955844583.458683, "reserves": 497936560.4544043, "bank_notes": 0.0, "open_market_operations": 23342381602.465096, "ach_payee_bank_3": 0.0}, "liabilities": {"deposits": 24896828022.720215, "receivables": 0.0, "loans_central_bank": 0.0, "ach_payer_bank_3": 0.0, "loans_interbank_bank_3": 0.0, "equity": 9899334723.657967}}}]},{"12": [{"bank_0": {"assets": {"interbank_loans": 0.0, "loans": 9469169112.002888, "reserves": 546184896.3488894, "bank_notes": 0.0, "open_market_operations": 33342135117.856853, "ach_payee_bank_0": 0.0}, "liabilities": {"deposits": 27309244817.444466, "receivables": 0.0, "loans_central_bank": 0.0, "ach_payer_bank_0": 0.0, "loans_interbank_bank_0": 0.0, "equity": 16048244308.764168}}}, {"bank_1": {"assets": {"interbank_loans": 0.0, "loans": 6500451523.843893, "reserves": 314096744.5947339, "bank_notes": 0.0, "open_market_operations": 21085295923.956882, "ach_payee_bank_1": 0.0}, "liabilities": {"deposits": 15704837229.736694, "receivables": 0.0, "loans_central_bank": 0.0, "ach_payer_bank_1": 0.0, "loans_interbank_bank_1": 0.0, "equity": 12195006962.658813}}}, {"bank_2": {"assets": {"interbank_loans": 0.0, "loans": 14459346845.61125, "reserves": 615421373.0755606, "bank_notes": 0.0, "open_market_operations": 31833382320.58772, "ach_payee_bank_2": 0.0}, "liabilities": {"deposits": 30771068653.778027, "receivables": 0.0, "loans_central_bank": 0.0, "ach_payer_bank_2": 0.0, "loans_interbank_bank_2": 0.0, "equity": 16137081885.496502}}}, {"bank_3": {"assets": {"interbank_loans": 0.0, "loans": 11441777384.827188, "reserves": 510754250.04885644, "bank_notes": 0.0, "open_market_operations": 24137723690.654556, "ach_payee_bank_3": 0.0}, "liabilities": {"deposits": 25537712502.44282, "receivables": 0.0, "loans_central_bank": 0.0, "ach_payer_bank_3": 0.0, "loans_interbank_bank_3": 0.0, "equity": 10552542823.08778}}}]},{"13": [{"bank_0": {"assets": {"interbank_loans": 0.0, "loans": 9903484399.231525, "reserves": 559168597.8711761, "bank_notes": 0.0, "open_market_operations": 34415144116.34078, "ach_payee_bank_0": 0.0}, "liabilities": {"deposits": 27958429893.558807, "receivables": 0.0, "loans_central_bank": 0.0, "ach_payer_bank_0": 0.0, "loans_interbank_bank_0": 0.0, "equity": 16919367219.884674}}}, {"bank_1": {"assets": {"interbank_loans": 0.0, "loans": 6950262055.912378, "reserves": 314933186.12216985, "bank_notes": 0.0, "open_market_operations": 21252204744.052258, "ach_payee_bank_1": 0.0}, "liabilities": {"deposits": 15746659306.108492, "receivables": 0.0, "loans_central_bank": 0.0, "ach_payer_bank_1": 0.0, "loans_interbank_bank_1": 0.0, "equity": 12770740679.978315}}}, {"bank_2": {"assets": {"interbank_loans": 0.0, "loans": 15062313849.43637, "reserves": 631063067.099071, "bank_notes": 0.0, "open_market_operations": 32905097084.116432, "ach_payee_bank_2": 0.0}, "liabilities": {"deposits": 31553153354.95355, "receivables": 0.0, "loans_central_bank": 0.0, "ach_payer_bank_2": 0.0, "loans_interbank_bank_2": 0.0, "equity": 17045320645.698322}}}, {"bank_3": {"assets": {"interbank_loans": 0.0, "loans": 12250983974.180573, "reserves": 526435931.2924831, "bank_notes": 0.0, "open_market_operations": 24776648435.08012, "ach_payee_bank_3": 0.0}, "liabilities": {"deposits": 26321796564.624153, "receivables": 0.0, "loans_central_bank": 0.0, "ach_payer_bank_3": 0.0, "loans_interbank_bank_3": 0.0, "equity": 11232271775.929024}}}]},{"14": [{"bank_0": {"assets": {"interbank_loans": 2192106.589876175, "loans": 10486890584.940798, "reserves": 572909191.6731226, "bank_notes": 0.0, "open_market_operations": 35406819345.42083, "ach_payee_bank_0": 0.0}, "liabilities": {"deposits": 28645459583.65613, "receivables": 0.0, "loans_central_bank": 0.0, "ach_payer_bank_0": 0.0, "loans_interbank_bank_0": 0.0, "equity": 17823351644.968494}}}, {"bank_1": {"assets": {"interbank_loans": 0.0, "loans": 7671927950.673504, "reserves": 317661405.781304, "bank_notes": 0.0, "open_market_operations": 21256080433.1542, "ach_payee_bank_1": 0.0}, "liabilities": {"deposits": 15883070289.065197, "receivables": 0.0, "loans_central_bank": 0.0, "ach_payer_bank_1": 0.0, "loans_interbank_bank_1": 2192106.589876175, "equity": 13360407393.953936}}}, {"bank_2": {"assets": {"interbank_loans": 0.0, "loans": 15699034197.508144, "reserves": 649360273.8079835, "bank_notes": 0.0, "open_market_operations": 34108503728.723194, "ach_payee_bank_2": 0.0}, "liabilities": {"deposits": 32468013690.399174, "receivables": 0.0, "loans_central_bank": 0.0, "ach_payer_bank_2": 0.0, "loans_interbank_bank_2": 0.0, "equity": 17988884509.64015}}}, {"bank_3": {"assets": {"interbank_loans": 0.0, "loans": 12974802748.466791, "reserves": 543597691.5316551, "bank_notes": 0.0, "open_market_operations": 25601528286.422596, "ach_payee_bank_3": 0.0}, "liabilities": {"deposits": 27179884576.582756, "receivables": 0.0, "loans_central_bank": 0.0, "ach_payer_bank_3": 0.0, "loans_interbank_bank_3": 0.0, "equity": 11940044149.838287}}}]},{"15": [{"bank_0": {"assets": {"interbank_loans": 0.0, "loans": 11190370168.553545, "reserves": 587581079.7084788, "bank_notes": 0.0, "open_market_operations": 36362000084.36475, "ach_payee_bank_0": 0.0}, "liabilities": {"deposits": 29379053985.42394, "receivables": 0.0, "loans_central_bank": 0.0, "ach_payer_bank_0": 0.0, "loans_interbank_bank_0": 0.0, "equity": 18760897347.20284}}}, {"bank_1": {"assets": {"interbank_loans": 0.0, "loans": 8439598908.800443, "reserves": 323414163.4182091, "bank_notes": 0.0, "open_market_operations": 21372354356.43236, "ach_payee_bank_1": 0.0}, "liabilities": {"deposits": 16170708170.910454, "receivables": 0.0, "loans_central_bank": 0.0, "ach_payer_bank_1": 0.0, "loans_interbank_bank_1": 0.0, "equity": 13964659257.740559}}}, {"bank_2": {"assets": {"interbank_loans": 0.0, "loans": 16296819302.225319, "reserves": 667750340.550538, "bank_notes": 0.0, "open_market_operations": 35393864027.9691, "ach_payee_bank_2": 0.0}, "liabilities": {"deposits": 33387517027.526894, "receivables": 0.0, "loans_central_bank": 0.0, "ach_payer_bank_2": 0.0, "loans_interbank_bank_2": 0.0, "equity": 18970916643.218063}}}, {"bank_3": {"assets": {"interbank_loans": 0.0, "loans": 13894234692.936497, "reserves": 562462926.417065, "bank_notes": 0.0, "open_market_operations": 26344851401.317406, "ach_payee_bank_3": 0.0}, "liabilities": {"deposits": 28123146320.85325, "receivables": 0.0, "loans_central_bank": 0.0, "ach_payer_bank_3": 0.0, "loans_interbank_bank_3": 0.0, "equity": 12678402699.817719}}}]},{"16": [{"bank_0": {"assets": {"interbank_loans": 0.0, "loans": 11953237100.945045, "reserves": 601820584.3616596, "bank_notes": 0.0, "open_market_operations": 37269185647.99076, "ach_payee_bank_0": 0.0}, "liabilities": {"deposits": 30091029218.08298, "receivables": 0.0, "loans_central_bank": 0.0, "ach_payer_bank_0": 0.0, "loans_interbank_bank_0": 0.0, "equity": 19733214115.21449}}}, {"bank_1": {"assets": {"interbank_loans": 0.0, "loans": 9094826180.759768, "reserves": 327133381.29787725, "bank_notes": 0.0, "open_market_operations": 21520929834.74677, "ach_payee_bank_1": 0.0}, "liabilities": {"deposits": 16356669064.893862, "receivables": 0.0, "loans_central_bank": 0.0, "ach_payer_bank_1": 0.0, "loans_interbank_bank_1": 0.0, "equity": 14586220331.910551}}}, {"bank_2": {"assets": {"interbank_loans": 0.0, "loans": 17155112143.722416, "reserves": 686333932.8706524, "bank_notes": 0.0, "open_market_operations": 36468005053.03353, "ach_payee_bank_2": 0.0}, "liabilities": {"deposits": 34316696643.532623, "receivables": 0.0, "loans_central_bank": 0.0, "ach_payer_bank_2": 0.0, "loans_interbank_bank_2": 0.0, "equity": 19992754486.09398}}}, {"bank_3": {"assets": {"interbank_loans": 0.0, "loans": 14514116493.443949, "reserves": 580965816.4712495, "bank_notes": 0.0, "open_market_operations": 27401845425.91628, "ach_payee_bank_3": 0.0}, "liabilities": {"deposits": 29048290823.562473, "receivables": 0.0, "loans_central_bank": 0.0, "ach_payer_bank_3": 0.0, "loans_interbank_bank_3": 0.0, "equity": 13448636912.269001}}}]},{"17": [{"bank_0": {"assets": {"interbank_loans": 0.0, "loans": 12655800484.724762, "reserves": 620247307.4367628, "bank_notes": 0.0, "open_market_operations": 38476796564.36643, "ach_payee_bank_0": 0.0}, "liabilities": {"deposits": 31012365371.838142, "receivables": 0.0, "loans_central_bank": 0.0, "ach_payer_bank_0": 0.0, "loans_interbank_bank_0": 0.0, "equity": 20740478984.68981}}}, {"bank_1": {"assets": {"interbank_loans": 0.0, "loans": 9783223540.55394, "reserves": 329979552.9381318, "bank_notes": 0.0, "open_market_operations": 21610190271.099083, "ach_payee_bank_1": 0.0}, "liabilities": {"deposits": 16498977646.90659, "receivables": 0.0, "loans_central_bank": 0.0, "ach_payer_bank_1": 0.0, "loans_interbank_bank_1": 0.0, "equity": 15224415717.684566}}}, {"bank_2": {"assets": {"interbank_loans": 0.0, "loans": 17984697239.04897, "reserves": 704971647.2160351, "bank_notes": 0.0, "open_market_operations": 37613153714.43939, "ach_payee_bank_2": 0.0}, "liabilities": {"deposits": 35248582360.80176, "receivables": 0.0, "loans_central_bank": 0.0, "ach_payer_bank_2": 0.0, "loans_interbank_bank_2": 0.0, "equity": 21054240239.902634}}}, {"bank_3": {"assets": {"interbank_loans": 0.0, "loans": 15457427546.875902, "reserves": 600676327.4581631, "bank_notes": 0.0, "open_market_operations": 28228623068.553905, "ach_payee_bank_3": 0.0}, "liabilities": {"deposits": 30033816372.908157, "receivables": 0.0, "loans_central_bank": 0.0, "ach_payer_bank_3": 0.0, "loans_interbank_bank_3": 0.0, "equity": 14252910569.979813}}}]},{"18": [{"bank_0": {"assets": {"interbank_loans": 0.0, "loans": 13410857675.876171, "reserves": 634820141.3975649, "bank_notes": 0.0, "open_market_operations": 39483028893.09022, "ach_payee_bank_0": 0.0}, "liabilities": {"deposits": 31741007069.878246, "receivables": 0.0, "loans_central_bank": 0.0, "ach_payer_bank_0": 0.0, "loans_interbank_bank_0": 0.0, "equity": 21787699640.485706}}}, {"bank_1": {"assets": {"interbank_loans": 0.0, "loans": 10482575275.39447, "reserves": 333628853.49635494, "bank_notes": 0.0, "open_market_operations": 21743977435.616676, "ach_payee_bank_1": 0.0}, "liabilities": {"deposits": 16681442674.817747, "receivables": 0.0, "loans_central_bank": 0.0, "ach_payer_bank_1": 0.0, "loans_interbank_bank_1": 0.0, "equity": 15878738889.689753}}}, {"bank_2": {"assets": {"interbank_loans": 0.0, "loans": 18696413492.92482, "reserves": 724293977.7099417, "bank_notes": 0.0, "open_market_operations": 38950644859.984604, "ach_payee_bank_2": 0.0}, "liabilities": {"deposits": 36214698885.497086, "receivables": 0.0, "loans_central_bank": 0.0, "ach_payer_bank_2": 0.0, "loans_interbank_bank_2": 0.0, "equity": 22156653445.122284}}}, {"bank_3": {"assets": {"interbank_loans": 0.0, "loans": 16340224838.205315, "reserves": 619602300.601747, "bank_notes": 0.0, "open_market_operations": 29111760674.8184, "ach_payee_bank_3": 0.0}, "liabilities": {"deposits": 30980115030.08735, "receivables": 0.0, "loans_central_bank": 0.0, "ach_payer_bank_3": 0.0, "loans_interbank_bank_3": 0.0, "equity": 15091472783.538116}}}]},{"19": [{"bank_0": {"assets": {"interbank_loans": 0.0, "loans": 14284900335.550549, "reserves": 652227971.7230177, "bank_notes": 0.0, "open_market_operations": 40546510661.755554, "ach_payee_bank_0": 0.0}, "liabilities": {"deposits": 32611398586.150883, "receivables": 0.0, "loans_central_bank": 0.0, "ach_payer_bank_0": 0.0, "loans_interbank_bank_0": 0.0, "equity": 22872240382.87824}}}, {"bank_1": {"assets": {"interbank_loans": 0.0, "loans": 11293813728.210865, "reserves": 341531892.8779444, "bank_notes": 0.0, "open_market_operations": 21991533173.24448, "ach_payee_bank_1": 0.0}, "liabilities": {"deposits": 17076594643.89722, "receivables": 0.0, "loans_central_bank": 0.0, "ach_payer_bank_1": 0.0, "loans_interbank_bank_1": 0.0, "equity": 16550284150.43607}}}, {"bank_2": {"assets": {"interbank_loans": 0.0, "loans": 19589864366.942028, "reserves": 742362482.0947206, "bank_notes": 0.0, "open_market_operations": 40088250440.99902, "ach_payee_bank_2": 0.0}, "liabilities": {"deposits": 37118124104.73603, "receivables": 0.0, "loans_central_bank": 0.0, "ach_payer_bank_2": 0.0, "loans_interbank_bank_2": 0.0, "equity": 23302353185.299736}}}, {"bank_3": {"assets": {"interbank_loans": 0.0, "loans": 17181947957.561367, "reserves": 639294344.7993075, "bank_notes": 0.0, "open_market_operations": 30108357154.933147, "ach_payee_bank_3": 0.0}, "liabilities": {"deposits": 31964717239.965374, "receivables": 0.0, "loans_central_bank": 0.0, "ach_payer_bank_3": 0.0, "loans_interbank_bank_3": 0.0, "equity": 15964882217.32845}}}]},{"20": [{"bank_0": {"assets": {"interbank_loans": 0.0, "loans": 15184412494.81209, "reserves": 668636567.4167811, "bank_notes": 0.0, "open_market_operations": 41575776356.76747, "ach_payee_bank_0": 0.0}, "liabilities": {"deposits": 33431828370.83905, "receivables": 0.0, "loans_central_bank": 0.0, "ach_payer_bank_0": 0.0, "loans_interbank_bank_0": 0.0, "equity": 23996997048.157288}}}, {"bank_1": {"assets": {"interbank_loans": 0.0, "loans": 12299659527.696135, "reserves": 348640361.34111726, "bank_notes": 0.0, "open_market_operations": 22026423375.169125, "ach_payee_bank_1": 0.0}, "liabilities": {"deposits": 17432018067.055862, "receivables": 0.0, "loans_central_bank": 0.0, "ach_payer_bank_1": 0.0, "loans_interbank_bank_1": 0.0, "equity": 17242705197.150513}}}, {"bank_2": {"assets": {"interbank_loans": 0.0, "loans": 20402381193.05435, "reserves": 764044620.460955, "bank_notes": 0.0, "open_market_operations": 41526217528.86017, "ach_payee_bank_2": 0.0}, "liabilities": {"deposits": 38202231023.04775, "receivables": 0.0, "loans_central_bank": 0.0, "ach_payer_bank_2": 0.0, "loans_interbank_bank_2": 0.0, "equity": 24490412319.32772}}}, {"bank_3": {"assets": {"interbank_loans": 0.0, "loans": 18031378736.05092, "reserves": 659170339.1431847, "bank_notes": 0.0, "open_market_operations": 31142957675.016357, "ach_payee_bank_3": 0.0}, "liabilities": {"deposits": 32958516957.159233, "receivables": 0.0, "loans_central_bank": 0.0, "ach_payer_bank_3": 0.0, "loans_interbank_bank_3": 0.0, "equity": 16874989793.051231}}}]},{"21": [{"bank_0": {"assets": {"interbank_loans": 0.0, "loans": 16095945322.558592, "reserves": 685442124.302073, "bank_notes": 0.0, "open_market_operations": 42652750971.809265, "ach_payee_bank_0": 0.0}, "liabilities": {"deposits": 34272106215.10365, "receivables": 0.0, "loans_central_bank": 0.0, "ach_payer_bank_0": 0.0, "loans_interbank_bank_0": 0.0, "equity": 25162032203.56628}}}, {"bank_1": {"assets": {"interbank_loans": 0.0, "loans": 13250588050.890024, "reserves": 355204956.79468536, "bank_notes": 0.0, "open_market_operations": 22109261321.51646, "ach_payee_bank_1": 0.0}, "liabilities": {"deposits": 17760247839.73427, "receivables": 0.0, "loans_central_bank": 0.0, "ach_payer_bank_1": 0.0, "loans_interbank_bank_1": 0.0, "equity": 17954806489.466904}}}, {"bank_2": {"assets": {"interbank_loans": 0.0, "loans": 21269004176.718857, "reserves": 785876078.238927, "bank_notes": 0.0, "open_market_operations": 42964563652.77775, "ach_payee_bank_2": 0.0}, "liabilities": {"deposits": 39293803911.94635, "receivables": 0.0, "loans_central_bank": 0.0, "ach_payer_bank_2": 0.0, "loans_interbank_bank_2": 0.0, "equity": 25725639995.789185}}}, {"bank_3": {"assets": {"interbank_loans": 0.0, "loans": 19094594614.81907, "reserves": 682564352.2696751, "bank_notes": 0.0, "open_market_operations": 32173972231.1747, "ach_payee_bank_3": 0.0}, "liabilities": {"deposits": 34128217613.483753, "receivables": 0.0, "loans_central_bank": 0.0, "ach_payer_bank_3": 0.0, "loans_interbank_bank_3": 0.0, "equity": 17822913584.77969}}}]},{"22": [{"bank_0": {"assets": {"interbank_loans": 0.0, "loans": 16974556539.971899, "reserves": 702165103.8934238, "bank_notes": 0.0, "open_market_operations": 43800261172.837685, "ach_payee_bank_0": 0.0}, "liabilities": {"deposits": 35108255194.67119, "receivables": 0.0, "loans_central_bank": 0.0, "ach_payer_bank_0": 0.0, "loans_interbank_bank_0": 0.0, "equity": 26368727622.031815}}}, {"bank_1": {"assets": {"interbank_loans": 0.0, "loans": 14008092155.26965, "reserves": 360847721.7302482, "bank_notes": 0.0, "open_market_operations": 22360380748.774605, "ach_payee_bank_1": 0.0}, "liabilities": {"deposits": 18042386086.51241, "receivables": 0.0, "loans_central_bank": 0.0, "ach_payer_bank_1": 0.0, "loans_interbank_bank_1": 0.0, "equity": 18686934539.262096}}}, {"bank_2": {"assets": {"interbank_loans": 0.0, "loans": 22047256322.575253, "reserves": 806117821.4213284, "bank_notes": 0.0, "open_market_operations": 44461673245.65677, "ach_payee_bank_2": 0.0}, "liabilities": {"deposits": 40305891071.06642, "receivables": 0.0, "loans_central_bank": 0.0, "ach_payer_bank_2": 0.0, "loans_interbank_bank_2": 0.0, "equity": 27009156318.58693}}}, {"bank_3": {"assets": {"interbank_loans": 0.0, "loans": 20230639918.362484, "reserves": 702668378.9995259, "bank_notes": 0.0, "open_market_operations": 33011769177.441875, "ach_payee_bank_3": 0.0}, "liabilities": {"deposits": 35133418949.976295, "receivables": 0.0, "loans_central_bank": 0.0, "ach_payer_bank_3": 0.0, "loans_interbank_bank_3": 0.0, "equity": 18811658524.82759}}}]},{"23": [{"bank_0": {"assets": {"interbank_loans": 0.0, "loans": 17820278802.23397, "reserves": 716942767.8905681, "bank_notes": 0.0, "open_market_operations": 44928235223.55326, "ach_payee_bank_0": 0.0}, "liabilities": {"deposits": 35847138394.528404, "receivables": 0.0, "loans_central_bank": 0.0, "ach_payer_bank_0": 0.0, "loans_interbank_bank_0": 0.0, "equity": 27618318399.14939}}}, {"bank_1": {"assets": {"interbank_loans": 0.0, "loans": 14882301403.879444, "reserves": 367431537.6541648, "bank_notes": 0.0, "open_market_operations": 22561702175.925995, "ach_payee_bank_1": 0.0}, "liabilities": {"deposits": 18371576882.70824, "receivables": 0.0, "loans_central_bank": 0.0, "ach_payer_bank_1": 0.0, "loans_interbank_bank_1": 0.0, "equity": 19439858234.75136}}}, {"bank_2": {"assets": {"interbank_loans": 0.0, "loans": 22994228825.9055, "reserves": 827152665.928464, "bank_notes": 0.0, "open_market_operations": 45877584674.646706, "ach_payee_bank_2": 0.0}, "liabilities": {"deposits": 41357633296.4232, "receivables": 0.0, "loans_central_bank": 0.0, "ach_payer_bank_2": 0.0, "loans_interbank_bank_2": 0.0, "equity": 28341332870.057465}}}, {"bank_3": {"assets": {"interbank_loans": 0.0, "loans": 21253001062.929985, "reserves": 724767776.0944943, "bank_notes": 0.0, "open_market_operations": 34099624970.637466, "ach_payee_bank_3": 0.0}, "liabilities": {"deposits": 36238388804.72472, "receivables": 0.0, "loans_central_bank": 0.0, "ach_payer_bank_3": 0.0, "loans_interbank_bank_3": 0.0, "equity": 19839005004.937225}}}]},{"24": [{"bank_0": {"assets": {"interbank_loans": 0.0, "loans": 18764767454.52337, "reserves": 735153686.774543, "bank_notes": 0.0, "open_market_operations": 46168175556.80333, "ach_payee_bank_0": 0.0}, "liabilities": {"deposits": 36757684338.72715, "receivables": 0.0, "loans_central_bank": 0.0, "ach_payer_bank_0": 0.0, "loans_interbank_bank_0": 0.0, "equity": 28910412359.374092}}}, {"bank_1": {"assets": {"interbank_loans": 0.0, "loans": 15718595738.95206, "reserves": 374457189.52210337, "bank_notes": 0.0, "open_market_operations": 22844155480.225105, "ach_payee_bank_1": 0.0}, "liabilities": {"deposits": 18722859476.105167, "receivables": 0.0, "loans_central_bank": 0.0, "ach_payer_bank_1": 0.0, "loans_interbank_bank_1": 0.0, "equity": 20214348932.594105}}}, {"bank_2": {"assets": {"interbank_loans": 0.0, "loans": 23946780706.12352, "reserves": 846734465.4998475, "bank_notes": 0.0, "open_market_operations": 47266491703.93857, "ach_payee_bank_2": 0.0}, "liabilities": {"deposits": 42336723274.99238, "receivables": 0.0, "loans_central_bank": 0.0, "ach_payer_bank_2": 0.0, "loans_interbank_bank_2": 0.0, "equity": 29723283600.569557}}}, {"bank_3": {"assets": {"interbank_loans": 0.0, "loans": 22382257653.585636, "reserves": 746874127.016869, "bank_notes": 0.0, "open_market_operations": 35122969429.23609, "ach_payee_bank_3": 0.0}, "liabilities": {"deposits": 37343706350.843445, "receivables": 0.0, "loans_central_bank": 0.0, "ach_payer_bank_3": 0.0, "loans_interbank_bank_3": 0.0, "equity": 20908394858.995148}}}]},{"25": [{"bank_0": {"assets": {"interbank_loans": 0.0, "loans": 19172357681.46422, "reserves": 726465353.4798168, "bank_notes": 0.0, "open_market_operations": 46715549491.04879, "ach_payee_bank_0": 0.0}, "liabilities": {"deposits": 36323267673.99084, "receivables": 0.0, "loans_central_bank": 0.0, "ach_payer_bank_0": 0.0, "loans_interbank_bank_0": 42416055.586811304, "equity": 30248688796.415176}}}, {"bank_1": {"assets": {"interbank_loans": 6736903089.767139, "loans": 16060019954.304491, "reserves": 557998523.356884, "bank_notes": 0.0, "open_market_operations": 25556595634.899055, "ach_payee_bank_1": 0.0}, "liabilities": {"deposits": 27899926167.84425, "receivables": 0.0, "loans_central_bank": 0.0, "ach_payer_bank_1": 0.0, "loans_interbank_bank_1": 0.0, "equity": 21011591034.483326}}}, {"bank_2": {"assets": {"interbank_loans": 0.0, "loans": 24466929639.818855, "reserves": 807670790.7792854, "bank_notes": 0.0, "open_market_operations": 47843668810.379196, "ach_payee_bank_2": 0.0}, "liabilities": {"deposits": 40383539538.96426, "receivables": 0.0, "loans_central_bank": 0.0, "ach_payer_bank_2": 0.0, "loans_interbank_bank_2": 1579696133.7440166, "equity": 31155033568.269066}}}, {"bank_3": {"assets": {"interbank_loans": 0.0, "loans": 22868423522.60502, "reserves": 634772740.3583002, "bank_notes": 0.0, "open_market_operations": 35370628039.246796, "ach_payee_bank_3": 0.0}, "liabilities": {"deposits": 31738637017.915028, "receivables": 0.0, "loans_central_bank": 0.0, "ach_payer_bank_3": 0.0, "loans_interbank_bank_3": 5114790900.436312, "equity": 22020396383.858772}}}]},{"26": [{"bank_0": {"assets": {"interbank_loans": 40900478.920684874, "loans": 12060796597.661295, "reserves": 581571554.4928069, "bank_notes": 0.0, "open_market_operations": 48009787515.99968, "ach_payee_bank_0": 0.0}, "liabilities": {"deposits": 29078577724.64034, "receivables": 0.0, "loans_central_bank": 0.0, "ach_payer_bank_0": 0.0, "loans_interbank_bank_0": 0.0, "equity": 31614478422.434124}}}, {"bank_1": {"assets": {"interbank_loans": 5937779227.128476, "loans": 8407906347.956958, "reserves": 394416231.2423229, "bank_notes": 0.0, "open_market_operations": 26790144572.94717, "ach_payee_bank_1": 0.0}, "liabilities": {"deposits": 19720811562.11616, "receivables": 0.0, "loans_central_bank": 0.0, "ach_payer_bank_1": 0.0, "loans_interbank_bank_1": 0.0, "equity": 21809434817.158764}}}, {"bank_2": {"assets": {"interbank_loans": 0.0, "loans": 18293008678.427563, "reserves": 683805254.3424294, "bank_notes": 0.0, "open_market_operations": 49141922599.803215, "ach_payee_bank_2": 0.0}, "liabilities": {"deposits": 34190262717.121464, "receivables": 0.0, "loans_central_bank": 0.0, "ach_payer_bank_2": 0.0, "loans_interbank_bank_2": 1297614733.360337, "equity": 32630859082.091408}}}, {"bank_3": {"assets": {"interbank_loans": 0.0, "loans": 16071781180.92534, "reserves": 500455984.9703288, "bank_notes": 0.0, "open_market_operations": 36330421738.76963, "ach_payee_bank_3": 0.0}, "liabilities": {"deposits": 25022799248.51646, "receivables": 0.0, "loans_central_bank": 0.0, "ach_payer_bank_3": 0.0, "loans_interbank_bank_3": 4681064972.688824, "equity": 23198794683.460014}}}]},{"27": [{"bank_0": {"assets": {"interbank_loans": 0.0, "loans": 12579537624.708368, "reserves": 587111174.6518381, "bank_notes": 0.0, "open_market_operations": 49113311288.60288, "ach_payee_bank_0": 0.0}, "liabilities": {"deposits": 29355558732.591904, "receivables": 0.0, "loans_central_bank": 0.0, "ach_payer_bank_0": 0.0, "loans_interbank_bank_0": 0.0, "equity": 32924401355.371185}}}, {"bank_1": {"assets": {"interbank_loans": 4924238398.422619, "loans": 8780999132.398083, "reserves": 396430058.5347729, "bank_notes": 0.0, "open_market_operations": 28266047298.10429, "ach_payee_bank_1": 0.0}, "liabilities": {"deposits": 19821502926.738647, "receivables": 0.0, "loans_central_bank": 0.0, "ach_payer_bank_1": 0.0, "loans_interbank_bank_1": 0.0, "equity": 22546211960.721115}}}, {"bank_2": {"assets": {"interbank_loans": 0.0, "loans": 18978146605.552307, "reserves": 699855782.2879118, "bank_notes": 0.0, "open_market_operations": 50475404935.52525, "ach_payee_bank_2": 0.0}, "liabilities": {"deposits": 34992789114.39559, "receivables": 0.0, "loans_central_bank": 0.0, "ach_payer_bank_2": 0.0, "loans_interbank_bank_2": 1098538208.4517803, "equity": 34062080000.518105}}}, {"bank_3": {"assets": {"interbank_loans": 0.0, "loans": 16668016716.037796, "reserves": 515425311.52221155, "bank_notes": 0.0, "open_market_operations": 36727980874.32272, "ach_payee_bank_3": 0.0}, "liabilities": {"deposits": 25771265576.11059, "receivables": 0.0, "loans_central_bank": 0.0, "ach_payer_bank_3": 0.0, "loans_interbank_bank_3": 3825700189.9708385, "equity": 24314457135.801308}}}]},{"28": [{"bank_0": {"assets": {"interbank_loans": 23137216.446047902, "loans": 13050971576.34319, "reserves": 596877894.3134446, "bank_notes": 0.0, "open_market_operations": 50446017246.925156, "ach_payee_bank_0": 0.0}, "liabilities": {"deposits": 29843894715.67223, "receivables": 0.0, "loans_central_bank": 0.0, "ach_payer_bank_0": 0.0, "loans_interbank_bank_0": 0.0, "equity": 34273109218.35561}}}, {"bank_1": {"assets": {"interbank_loans": 3580582741.5635366, "loans": 9138305815.381157, "reserves": 399539170.79966736, "bank_notes": 0.0, "open_market_operations": 30188790643.509, "ach_payee_bank_1": 0.0}, "liabilities": {"deposits": 19976958539.98335, "receivables": 0.0, "loans_central_bank": 0.0, "ach_payer_bank_1": 0.0, "loans_interbank_bank_1": 0.0, "equity": 23330259831.270008}}}, {"bank_2": {"assets": {"interbank_loans": 0.0, "loans": 19645112842.801525, "reserves": 716080696.2008665, "bank_notes": 0.0, "open_market_operations": 51248429813.71839, "ach_payee_bank_2": 0.0}, "liabilities": {"deposits": 35804034810.04332, "receivables": 0.0, "loans_central_bank": 0.0, "ach_payer_bank_2": 0.0, "loans_interbank_bank_2": 268253660.29068303, "equity": 35537334882.38678}}}, {"bank_3": {"assets": {"interbank_loans": 0.0, "loans": 17324610125.82215, "reserves": 523873653.9564972, "bank_notes": 0.0, "open_market_operations": 37127964850.217766, "ach_payee_bank_3": 0.0}, "liabilities": {"deposits": 26193682697.82486, "receivables": 0.0, "loans_central_bank": 0.0, "ach_payer_bank_3": 0.0, "loans_interbank_bank_3": 3335466297.7189016, "equity": 25447299634.452652}}}]},{"29": [{"bank_0": {"assets": {"interbank_loans": 0.0, "loans": 13498390804.18129, "reserves": 604760743.7235657, "bank_notes": 0.0, "open_market_operations": 51798826950.86665, "ach_payee_bank_0": 0.0}, "liabilities": {"deposits": 30238037186.178284, "receivables": 0.0, "loans_central_bank": 0.0, "ach_payer_bank_0": 0.0, "loans_interbank_bank_0": 0.0, "equity": 35663941312.59322}}}, {"bank_1": {"assets": {"interbank_loans": 2520707746.722142, "loans": 9681188736.498466, "reserves": 400457413.6860161, "bank_notes": 0.0, "open_market_operations": 31593397602.271362, "ach_payee_bank_1": 0.0}, "liabilities": {"deposits": 20022870684.300797, "receivables": 0.0, "loans_central_bank": 0.0, "ach_payer_bank_1": 0.0, "loans_interbank_bank_1": 0.0, "equity": 24172880814.87719}}}, {"bank_2": {"assets": {"interbank_loans": 0.0, "loans": 20492204895.357807, "reserves": 733329506.6807103, "bank_notes": 0.0, "open_market_operations": 52639072919.943924, "ach_payee_bank_2": 0.0}, "liabilities": {"deposits": 36666475334.035515, "receivables": 0.0, "loans_central_bank": 0.0, "ach_payer_bank_2": 0.0, "loans_interbank_bank_2": 157187572.8454857, "equity": 37040944415.10144}}}, {"bank_3": {"assets": {"interbank_loans": 0.0, "loans": 17846681446.122673, "reserves": 538910177.8118098, "bank_notes": 0.0, "open_market_operations": 37524993578.67763, "ach_payee_bank_3": 0.0}, "liabilities": {"deposits": 26945508890.590477, "receivables": 0.0, "loans_central_bank": 0.0, "ach_payer_bank_3": 0.0, "loans_interbank_bank_3": 2363520173.8766565, "equity": 26601556138.144974}}}]},{"30": [{"bank_0": {"assets": {"interbank_loans": 0.0, "loans": 14049336243.355846, "reserves": 616257032.3990442, "bank_notes": 0.0, "open_market_operations": 53245005284.097145, "ach_payee_bank_0": 0.0}, "liabilities": {"deposits": 30812851619.95221, "receivables": 0.0, "loans_central_bank": 0.0, "ach_payer_bank_0": 0.0, "loans_interbank_bank_0": 0.0, "equity": 37097746939.899826}}}, {"bank_1": {"assets": {"interbank_loans": 1717939641.4210277, "loans": 10089809803.04185, "reserves": 402708155.82137585, "bank_notes": 0.0, "open_market_operations": 32989956122.794395, "ach_payee_bank_1": 0.0}, "liabilities": {"deposits": 20135407791.0688, "receivables": 0.0, "loans_central_bank": 0.0, "ach_payer_bank_1": 0.0, "loans_interbank_bank_1": 0.0, "equity": 25065005932.009842}}}, {"bank_2": {"assets": {"interbank_loans": 6865795.007834792, "loans": 21229438135.71209, "reserves": 749196402.8103098, "bank_notes": 0.0, "open_market_operations": 54067451587.15972, "ach_payee_bank_2": 0.0}, "liabilities": {"deposits": 37459820140.51549, "receivables": 0.0, "loans_central_bank": 0.0, "ach_payer_bank_2": 0.0, "loans_interbank_bank_2": 0.0, "equity": 38593131780.17447}}}, {"bank_3": {"assets": {"interbank_loans": 0.0, "loans": 18587629636.65912, "reserves": 551283359.6803856, "bank_notes": 0.0, "open_market_operations": 37921398353.72111, "ach_payee_bank_3": 0.0}, "liabilities": {"deposits": 27564167984.019287, "receivables": 0.0, "loans_central_bank": 0.0, "ach_payer_bank_3": 0.0, "loans_interbank_bank_3": 1724805436.4288626, "equity": 27771337929.612457}}}]}]