[{"0": [{"bank_0": {"assets": {"interbank_loans": 0.0, "loans": 5632285560.0, "reserves": 360243880.6399994, "bank_notes": 0.0, "open_market_operations": 18587047656.36, "ach_payee_bank_0": 0.0}, "liabilities": {"deposits": 18012194032.0, "receivables": 0.0, "loans_central_bank": 0.0, "ach_payer_bank_0": 0.0, "loans_interbank_bank_0": 0.0, "equity": 6567383065.0}}}, {"bank_1": {"assets": {"interbank_loans": 0.0, "loans": 6416665460.0, "reserves": 412622541.5400009, "bank_notes": 0.0, "open_market_operations": 19054025605.46, "ach_payee_bank_1": 0.0}, "liabilities": {"deposits": 20631127077.0, "receivables": 0.0, "loans_central_bank": 0.0, "ach_payer_bank_1": 0.0, "loans_interbank_bank_1": 0.0, "equity": 5252186530.0}}}, {"bank_2": {"assets": {"interbank_loans": 0.0, "loans": 6193102913.0, "reserves": 387142500.9399986, "bank_notes": 0.0, "open_market_operations": 18689787196.06, "ach_payee_bank_2": 0.0}, "liabilities": {"deposits": 19357125047.0, "receivables": 0.0, "loans_central_bank": 0.0, "ach_payer_bank_2": 0.0, "loans_interbank_bank_2": 0.0, "equity": 5912907563.0}}}, {"bank_3": {"assets": {"interbank_loans": 0.0, "loans": 5087761866.0, "reserves": 315907132.47999954, "bank_notes": 0.0, "open_market_operations": 15989026348.52, "ach_payee_bank_3": 0.0}, "liabilities": {"deposits": 15795356624.0, "receivables": 0.0, "loans_central_bank": 0.0, "ach_payer_bank_3": 0.0, "loans_interbank_bank_3": 0.0, "equity": 5597338723.0}}}]},{"1": [{"bank_0": {"assets": {"interbank_loans": 0.0, "loans": 5754967900.238072, "reserves": 350708505.29032177, "bank_notes": 0.0, "open_market_operations": 19100948722.17778, "ach_payee_bank_0": 558621741.7862042}, "liabilities": {"deposits": 17535425264.516087, "receivables": 558621741.7862042, "loans_central_bank": 0.0, "ach_payer_bank_0": 634950389.6660335, "loans_interbank_bank_0": 0.0, "equity": 7036249473.524052}}}, {"bank_1": {"assets": {"interbank_loans": 0.0, "loans": 6556042094.2899475, "reserves": 407764894.2182007, "bank_notes": 0.0, "open_market_operations": 19575920544.468433, "ach_payee_bank_1": 601284315.268703}, "liabilities": {"deposits": 20388244710.910034, "receivables": 601284315.268703, "loans_central_bank": 0.0, "ach_payer_bank_1": 423670085.57018495, "loans_interbank_bank_1": 0.0, "equity": 5727812736.496361}}}, {"bank_2": {"assets": {"interbank_loans": 0.0, "loans": 6327623536.711184, "reserves": 376425811.33381194, "bank_notes": 0.0, "open_market_operations": 19207657447.55084, "ach_payee_bank_2": 661505443.544795}, "liabilities": {"deposits": 18821290566.690598, "receivables": 661505443.544795, "loans_central_bank": 0.0, "ach_payer_bank_2": 705458295.8130124, "loans_interbank_bank_2": 0.0, "equity": 6384957933.092224}}}, {"bank_3": {"assets": {"interbank_loans": 0.0, "loans": 5198273334.826337, "reserves": 307843446.09996194, "bank_notes": 0.0, "open_market_operations": 16430957557.23485, "ach_payee_bank_3": 484264119.78832805}, "liabilities": {"deposits": 15392172304.998096, "receivables": 484264119.78832805, "loans_central_bank": 0.0, "ach_payer_bank_3": 541596849.3388, "loans_interbank_bank_3": 0.0, "equity": 6003305183.824249}}}]},{"2": [{"bank_0": {"assets": {"interbank_loans": 0.0, "loans": 5914831459.035683, "reserves": 364695897.169047, "bank_notes": 0.0, "open_market_operations": 19424704199.50758, "ach_payee_bank_0": 0.0}, "liabilities": {"deposits": 18234794858.45235, "receivables": 2.384185791015625e-07, "loans_central_bank": 0.0, "ach_payer_bank_0": 0.0, "loans_interbank_bank_0": 0.0, "equity": 7469436697.25996}}}, {"bank_1": {"assets": {"interbank_loans": 0.0, "loans": 6709084898.054872, "reserves": 422150905.24749213, "bank_notes": 0.0, "open_market_operations": 20149599241.80821, "ach_payee_bank_1": 0.0}, "liabilities": {"deposits": 21107545262.374607, "receivables": 2.980232238769531e-07, "loans_central_bank": 0.0, "ach_payer_bank_1": 0.0, "loans_interbank_bank_1": 0.0, "equity": 6173289782.735966}}}, {"bank_2": {"assets": {"interbank_loans": 0.0, "loans": 6491312262.818291, "reserves": 396402742.1946127, "bank_notes": 0.0, "open_market_operations": 19755100319.776665, "ach_payee_bank_2": 0.0}, "liabilities": {"deposits": 19820137109.730633, "receivables": -5.364418029785156e-07, "loans_central_bank": 0.0, "ach_payer_bank_2": 0.0, "loans_interbank_bank_2": 0.0, "equity": 6822678215.058933}}}, {"bank_3": {"assets": {"interbank_loans": 0.0, "loans": 5345696245.226441, "reserves": 320374292.32779247, "bank_notes": 0.0, "open_market_operations": 16733174445.473404, "ach_payee_bank_3": 0.0}, "liabilities": {"deposits": 16018714616.389622, "receivables": 3.2782554626464844e-07, "loans_central_bank": 0.0, "ach_payer_bank_3": 0.0, "loans_interbank_bank_3": 0.0, "equity": 6380530366.638016}}}]},{"3": [{"bank_0": {"assets": {"interbank_loans": 0.0, "loans": 6123173380.898869, "reserves": 358016699.69109315, "bank_notes": 0.0, "open_market_operations": 19958479175.016262, "ach_payee_bank_0": 567352747.4167368}, "liabilities": {"deposits": 17900834984.554657, "receivables": 567352747.4167371, "loans_central_bank": 0.0, "ach_payer_bank_0": 573614507.8184611, "loans_interbank_bank_0": 0.0, "equity": 7965219763.233105}}}, {"bank_1": {"assets": {"interbank_loans": 0.0, "loans": 6908806466.910418, "reserves": 415161974.5721128, "bank_notes": 0.0, "open_market_operations": 20703354217.427402, "ach_payee_bank_1": 558614106.0256039}, "liabilities": {"deposits": 20758098728.60564, "receivables": 558614106.0256041, "loans_central_bank": 0.0, "ach_payer_bank_1": 588402320.901579, "loans_interbank_bank_1": 0.0, "equity": 6680821609.402714}}}, {"bank_2": {"assets": {"interbank_loans": 0.0, "loans": 6642651116.3108015, "reserves": 389065750.1978658, "bank_notes": 0.0, "open_market_operations": 20298498497.88876, "ach_payee_bank_2": 676884138.7128133}, "liabilities": {"deposits": 19453287509.893288, "receivables": 676884138.7128127, "loans_central_bank": 0.0, "ach_payer_bank_2": 550871539.312976, "loans_interbank_bank_2": 0.0, "equity": 7326056315.191162}}}, {"bank_3": {"assets": {"interbank_loans": 0.0, "loans": 5488631952.813354, "reserves": 311780081.0818493, "bank_notes": 0.0, "open_market_operations": 17195828883.97801, "ach_payee_bank_3": 506939360.08372307}, "liabilities": {"deposits": 15589004054.092464, "receivables": 506939360.0837234, "loans_central_bank": 0.0, "ach_payer_bank_3": 596901984.2058612, "loans_interbank_bank_3": 0.0, "equity": 6810334879.5748825}}}]},{"4": [{"bank_0": {"assets": {"interbank_loans": 0.0, "loans": 6380824799.340759, "reserves": 374088434.1797136, "bank_notes": 0.0, "open_market_operations": 20376913939.40167, "ach_payee_bank_0": 0.0}, "liabilities": {"deposits": 18704421708.98568, "receivables": 2.980232238769531e-07, "loans_central_bank": 0.0, "ach_payer_bank_0": 0.0, "loans_interbank_bank_0": 0.0, "equity": 8427405463.936462}}}, {"bank_1": {"assets": {"interbank_loans": 0.0, "loans": 7098477851.532233, "reserves": 433203165.31605476, "bank_notes": 0.0, "open_market_operations": 21287923951.11855, "ach_payee_bank_1": 0.0}, "liabilities": {"deposits": 21660158265.80274, "receivables": 2.384185791015625e-07, "loans_central_bank": 0.0, "ach_payer_bank_1": 0.0, "loans_interbank_bank_1": 0.0, "equity": 7159446702.164097}}}, {"bank_2": {"assets": {"interbank_loans": 0.0, "loans": 6812799590.9361315, "reserves": 408000099.505753, "bank_notes": 0.0, "open_market_operations": 20983686846.002758, "ach_payee_bank_2": 0.0}, "liabilities": {"deposits": 20400004975.287647, "receivables": 2.384185791015625e-07, "loans_central_bank": 0.0, "ach_payer_bank_2": 0.0, "loans_interbank_bank_2": 0.0, "equity": 7804481561.156994}}}, {"bank_3": {"assets": {"interbank_loans": 0.0, "loans": 5692079128.28936, "reserves": 323332212.17571473, "bank_notes": 0.0, "open_market_operations": 17364096448.453266, "ach_payee_bank_3": 0.0}, "liabilities": {"deposits": 16166610608.785736, "receivables": -5.960464477539063e-08, "loans_central_bank": 0.0, "ach_payer_bank_3": 0.0, "loans_interbank_bank_3": 0.0, "equity": 7212897180.1326065}}}]},{"5": [{"bank_0": {"assets": {"interbank_loans": 0.0, "loans": 6692078183.949003, "reserves": 369833193.3840544, "bank_notes": 0.0, "open_market_operations": 20934103484.701508, "ach_payee_bank_0": 536423954.91524184}, "liabilities": {"deposits": 18491659669.20272, "receivables": 536423954.9152422, "loans_central_bank": 0.0, "ach_payer_bank_0": 549321552.6790401, "loans_interbank_bank_0": 0.0, "equity": 8955033640.152805}}}, {"bank_1": {"assets": {"interbank_loans": 0.0, "loans": 7376623492.620485, "reserves": 427407243.6241698, "bank_notes": 0.0, "open_market_operations": 21871374735.526863, "ach_payee_bank_1": 554074698.33107}, "liabilities": {"deposits": 21370362181.208492, "receivables": 554074698.3310702, "loans_central_bank": 0.0, "ach_payer_bank_1": 603560396.3085859, "loans_interbank_bank_1": 0.0, "equity": 7701482894.25444}}}, {"bank_2": {"assets": {"interbank_loans": 0.0, "loans": 7003744036.6824045, "reserves": 399512578.14574325, "bank_notes": 0.0, "open_market_operations": 21561573655.529392, "ach_payee_bank_2": 682742184.335844}, "liabilities": {"deposits": 19975628907.287163, "receivables": 682742184.3358443, "loans_central_bank": 0.0, "ach_payer_bank_2": 646101863.343397, "loans_interbank_bank_2": 0.0, "equity": 8343099499.726978}}}, {"bank_3": {"assets": {"interbank_loans": 0.0, "loans": 5932818846.289395, "reserves": 318410798.1826911, "bank_notes": 0.0, "open_market_operations": 17840198367.090996, "ach_payee_bank_3": 530581303.12803483}, "liabilities": {"deposits": 15920539909.134556, "receivables": 530581303.1280348, "loans_central_bank": 0.0, "ach_payer_bank_3": 504838328.3791679, "loans_interbank_bank_3": 0.0, "equity": 7666049774.049358}}}]},{"6": [{"bank_0": {"assets": {"interbank_loans": 0.0, "loans": 7047476513.926315, "reserves": 387290293.9459222, "bank_notes": 0.0, "open_market_operations": 21384821009.522655, "ach_payee_bank_0": 0.0}, "liabilities": {"deposits": 19364514697.29611, "receivables": 4.172325134277344e-07, "loans_central_bank": 0.0, "ach_payer_bank_0": 0.0, "loans_interbank_bank_0": 0.0, "equity": 9455073120.098785}}}, {"bank_1": {"assets": {"interbank_loans": 0.0, "loans": 7691313418.234876, "reserves": 444121169.71627885, "bank_notes": 0.0, "open_market_operations": 22282556129.501766, "ach_payee_bank_1": 0.0}, "liabilities": {"deposits": 22206058485.813942, "receivables": 5.066394805908203e-07, "loans_central_bank": 0.0, "ach_payer_bank_1": 0.0, "loans_interbank_bank_1": 0.0, "equity": 8211932231.638977}}}, {"bank_2": {"assets": {"interbank_loans": 0.0, "loans": 7184632751.168591, "reserves": 422387153.2209813, "bank_notes": 0.0, "open_market_operations": 22363002566.295433, "ach_payee_bank_2": 0.0}, "liabilities": {"deposits": 21119357661.049065, "receivables": 5.960464477539063e-08, "loans_central_bank": 0.0, "ach_payer_bank_2": 0.0, "loans_interbank_bank_2": 0.0, "equity": 8850664809.63594}}}, {"bank_3": {"assets": {"interbank_loans": 0.0, "loans": 6248691540.805389, "reserves": 332324156.40926254, "bank_notes": 0.0, "open_market_operations": 18129432375.51266, "ach_payee_bank_3": 0.0}, "liabilities": {"deposits": 16616207820.463127, "receivables": -6.854534149169922e-07, "loans_central_bank": 0.0, "ach_payer_bank_3": 0.0, "loans_interbank_bank_3": 0.0, "equity": 8094240252.264187}}}]},{"7": [{"bank_0": {"assets": {"interbank_loans": 0.0, "loans": 7434528677.594351, "reserves": 381746372.7436952, "bank_notes": 0.0, "open_market_operations": 21970649127.19403, "ach_payee_bank_0": 479366474.05192316}, "liabilities": {"deposits": 19087318637.18476, "receivables": 479366474.0519235, "loans_central_bank": 0.0, "ach_payer_bank_0": 680858288.6056451, "loans_interbank_bank_0": 0.0, "equity": 10018747251.741673}}}, {"bank_1": {"assets": {"interbank_loans": 0.0, "loans": 8027805645.750778, "reserves": 442222648.6429419, "bank_notes": 0.0, "open_market_operations": 22889099186.675213, "ach_payee_bank_1": 583968743.616211}, "liabilities": {"deposits": 22111132432.147095, "receivables": 583968743.6162117, "loans_central_bank": 0.0, "ach_payer_bank_1": 458943596.23050886, "loans_interbank_bank_1": 0.0, "equity": 8789051452.691326}}}, {"bank_2": {"assets": {"interbank_loans": 0.0, "loans": 7434332994.044492, "reserves": 416872061.32105434, "bank_notes": 0.0, "open_market_operations": 22975345134.98563, "ach_payee_bank_2": 662447995.765277}, "liabilities": {"deposits": 20843603066.052715, "receivables": 662447995.7652771, "loans_central_bank": 0.0, "ach_payer_bank_2": 554463173.5805061, "loans_interbank_bank_2": 0.0, "equity": 9428483950.717957}}}, {"bank_3": {"assets": {"interbank_loans": 0.0, "loans": 6526624644.481492, "reserves": 327450271.684543, "bank_notes": 0.0, "open_market_operations": 18626254408.589027, "ach_payee_bank_3": 499986654.5812788}, "liabilities": {"deposits": 16372513584.22715, "receivables": 499986654.5812781, "loans_central_bank": 0.0, "ach_payer_bank_3": 531504809.59803003, "loans_interbank_bank_3": 0.0, "equity": 8576310930.929886}}}]},{"8": [{"bank_0": {"assets": {"interbank_loans": 0.0, "loans": 7817857543.140555, "reserves": 398427908.2409626, "bank_notes": 0.0, "open_market_operations": 22259664150.50989, "ach_payee_bank_0": 0.0}, "liabilities": {"deposits": 19921395412.04813, "receivables": -1.1920928955078125e-07, "loans_central_bank": 0.0, "ach_payer_bank_0": 0.0, "loans_interbank_bank_0": 0.0, "equity": 10554554189.84328}}}, {"bank_1": {"assets": {"interbank_loans": 0.0, "loans": 8437608852.733267, "reserves": 463255594.49125767, "bank_notes": 0.0, "open_market_operations": 23599485444.07326, "ach_payee_bank_1": 0.0}, "liabilities": {"deposits": 23162779724.56288, "receivables": 4.172325134277344e-07, "loans_central_bank": 0.0, "ach_payer_bank_1": 0.0, "loans_interbank_bank_1": 0.0, "equity": 9337570166.734905}}}, {"bank_2": {"assets": {"interbank_loans": 0.0, "loans": 7677910982.023627, "reserves": 439715208.8703171, "bank_notes": 0.0, "open_market_operations": 23848493574.634678, "ach_payee_bank_2": 0.0}, "liabilities": {"deposits": 21985760443.515854, "receivables": 2.980232238769531e-07, "loans_central_bank": 0.0, "ach_payer_bank_2": 0.0, "loans_interbank_bank_2": 0.0, "equity": 9980359322.012768}}}, {"bank_3": {"assets": {"interbank_loans": 0.0, "loans": 6896997860.571784, "reserves": 340510337.5405096, "bank_notes": 0.0, "open_market_operations": 18824177475.293148, "ach_payee_bank_3": 0.0}, "liabilities": {"deposits": 17025516877.025478, "receivables": -1.1324882507324219e-06, "loans_central_bank": 0.0, "ach_payer_bank_3": 0.0, "loans_interbank_bank_3": 0.0, "equity": 9036168796.379965}}}]},{"9": [{"bank_0": {"assets": {"interbank_loans": 0.0, "loans": 8234336309.488227, "reserves": 393879751.243843, "bank_notes": 0.0, "open_market_operations": 22868235662.179935, "ach_payee_bank_0": 547480499.4193091}, "liabilities": {"deposits": 19693987562.19215, "receivables": 547480499.419309, "loans_central_bank": 0.0, "ach_payer_bank_0": 648643074.2736509, "loans_interbank_bank_0": 0.0, "equity": 11153821086.446201}}}, {"bank_1": {"assets": {"interbank_loans": 0.0, "loans": 8882888201.372019, "reserves": 464282740.4209306, "bank_notes": 0.0, "open_market_operations": 24238838147.0982, "ach_payee_bank_1": 439894967.9032719}, "liabilities": {"deposits": 23214137021.04653, "receivables": 439894967.90327233, "loans_central_bank": 0.0, "ach_payer_bank_1": 413620671.89846283, "loans_interbank_bank_1": 0.0, "equity": 9958251395.946156}}}, {"bank_2": {"assets": {"interbank_loans": 0.0, "loans": 8163952572.737125, "reserves": 438943819.3883045, "bank_notes": 0.0, "open_market_operations": 24496401731.115788, "ach_payee_bank_2": 633768753.0116379}, "liabilities": {"deposits": 21947190969.415222, "receivables": 633768753.0116382, "loans_central_bank": 0.0, "ach_payer_bank_2": 550497053.344548, "loans_interbank_bank_2": 0.0, "equity": 10601610100.48145}}}, {"bank_3": {"assets": {"interbank_loans": 0.0, "loans": 7369521852.695812, "reserves": 339289765.8204322, "bank_notes": 0.0, "open_market_operations": 19336198333.608044, "ach_payee_bank_3": 524551459.56695503}, "liabilities": {"deposits": 16964488291.02161, "receivables": 524551459.5669539, "loans_central_bank": 0.0, "ach_payer_bank_3": 532934880.3845122, "loans_interbank_bank_3": 0.0, "equity": 9547586780.718166}}}]},{"10": [{"bank_0": {"assets": {"interbank_loans": 0.0, "loans": 8675116881.80625, "reserves": 413108584.45559716, "bank_notes": 0.0, "open_market_operations": 23287177913.689465, "ach_payee_bank_0": 0.0}, "liabilities": {"deposits": 20655429222.779858, "receivables": 1.7881393432617188e-07, "loans_central_bank": 0.0, "ach_payer_bank_0": 0.0, "loans_interbank_bank_0": 0.0, "equity": 11719974157.171452}}}, {"bank_1": {"assets": {"interbank_loans": 0.0, "loans": 9343587061.5663, "reserves": 479710438.7805612, "bank_notes": 0.0, "open_market_operations": 24717327967.811523, "ach_payee_bank_1": 0.0}, "liabilities": {"deposits": 23985521939.02806, "receivables": 2.980232238769531e-07, "loans_central_bank": 0.0, "ach_payer_bank_1": 0.0, "loans_interbank_bank_1": 0.0, "equity": 10555103529.130325}}}, {"bank_2": {"assets": {"interbank_loans": 0.0, "loans": 8549103364.693897, "reserves": 463603145.91433257, "bank_notes": 0.0, "open_market_operations": 25367921470.182583, "ach_payee_bank_2": 0.0}, "liabilities": {"deposits": 23180157295.71663, "receivables": 7.152557373046875e-07, "loans_central_bank": 0.0, "ach_payer_bank_2": 0.0, "loans_interbank_bank_2": 0.0, "equity": 11200470685.074188}}}, {"bank_3": {"assets": {"interbank_loans": 0.0, "loans": 7834618591.350916, "reserves": 358077732.13607585, "bank_notes": 0.0, "open_market_operations": 19746354032.50844, "ach_payee_bank_3": 0.0}, "liabilities": {"deposits": 17903886606.80379, "receivables": -8.642673492431641e-07, "loans_central_bank": 0.0, "ach_payer_bank_3": 0.0, "loans_interbank_bank_3": 0.0, "equity": 10035163749.191639}}}]},{"11": [{"bank_0": {"assets": {"interbank_loans": 0.0, "loans": 9259554564.977638, "reserves": 411479991.01452744, "bank_notes": 0.0, "open_market_operations": 23920711787.874397, "ach_payee_bank_0": 504907490.106971}, "liabilities": {"deposits": 20573999550.72637, "receivables": 504907490.1069712, "loans_central_bank": 0.0, "ach_payer_bank_0": 658435487.610755, "loans_interbank_bank_0": 0.0, "equity": 12359311305.529434}}}, {"bank_1": {"assets": {"interbank_loans": 0.0, "loans": 9736351161.97019, "reserves": 477958510.3628153, "bank_notes": 0.0, "open_market_operations": 25389792772.071396, "ach_payee_bank_1": 511800291.25208014}, "liabilities": {"deposits": 23897925518.140766, "receivables": 511800291.25208044, "loans_central_bank": 0.0, "ach_payer_bank_1": 487589930.420308, "loans_interbank_bank_1": 0.0, "equity": 11218586995.843334}}}, {"bank_2": {"assets": {"interbank_loans": 0.0, "loans": 9003909039.944237, "reserves": 463480991.91776603, "bank_notes": 0.0, "open_market_operations": 26056410570.054565, "ach_payee_bank_2": 621379031.691112}, "liabilities": {"deposits": 23174049595.8883, "receivables": 621379031.6911128, "loans_central_bank": 0.0, "ach_payer_bank_2": 478342495.5488849, "loans_interbank_bank_2": 0.0, "equity": 11871408510.479374}}}, {"bank_3": {"assets": {"interbank_loans": 0.0, "loans": 8298192611.220124, "reserves": 357234449.89304876, "bank_notes": 0.0, "open_market_operations": 20283021167.46676, "ach_payee_bank_3": 478732472.01117206}, "liabilities": {"deposits": 17861722494.65244, "receivables": 478732472.01117116, "loans_central_bank": 0.0, "ach_payer_bank_3": 492451371.4813871, "loans_interbank_bank_3": 0.0, "equity": 10584274362.44611}}}]},{"12": [{"bank_0": {"assets": {"interbank_loans": 0.0, "loans": 9926054531.657213, "reserves": 431540628.94070345, "bank_notes": 0.0, "open_market_operations": 24189417332.80412, "ach_payee_bank_0": 0.0}, "liabilities": {"deposits": 21577031447.03517, "receivables": 8.940696716308594e-08, "loans_central_bank": 0.0, "ach_payer_bank_0": 0.0, "loans_interbank_bank_0": 0.0, "equity": 12969981046.366867}}}, {"bank_1": {"assets": {"interbank_loans": 0.0, "loans": 10248907389.578115, "reserves": 496115196.44461715, "bank_notes": 0.0, "open_market_operations": 25912954052.111794, "ach_payee_bank_1": 0.0}, "liabilities": {"deposits": 24805759822.230858, "receivables": 6.556510925292969e-07, "loans_central_bank": 0.0, "ach_payer_bank_1": 0.0, "loans_interbank_bank_1": 0.0, "equity": 11852216815.903664}}}, {"bank_2": {"assets": {"interbank_loans": 0.0, "loans": 9417716336.679083, "reserves": 487335895.4700446, "bank_notes": 0.0, "open_market_operations": 26979036924.13805, "ach_payee_bank_2": 0.0}, "liabilities": {"deposits": 24366794773.50223, "receivables": 5.960464477539063e-08, "loans_central_bank": 0.0, "ach_payer_bank_2": 0.0, "loans_interbank_bank_2": 0.0, "equity": 12517294382.784946}}}, {"bank_3": {"assets": {"interbank_loans": 0.0, "loans": 8742644085.026995, "reserves": 377462142.3818313, "bank_notes": 0.0, "open_market_operations": 20864253927.924774, "ach_payee_bank_3": 0.0}, "liabilities": {"deposits": 18873107119.091564, "receivables": -8.046627044677734e-07, "loans_central_bank": 0.0, "ach_payer_bank_3": 0.0, "loans_interbank_bank_3": 0.0, "equity": 11111253036.242039}}}]},{"13": [{"bank_0": {"assets": {"interbank_loans": 0.0, "loans": 10694064836.176292, "reserves": 433063557.04032534, "bank_notes": 0.0, "open_market_operations": 24844282250.727272, "ach_payee_bank_0": 532422945.96936804}, "liabilities": {"deposits": 21653177852.016266, "receivables": 532422945.9693681, "loans_central_bank": 0.0, "ach_payer_bank_0": 665336240.8058611, "loans_interbank_bank_0": 0.0, "equity": 13652896551.121765}}}, {"bank_1": {"assets": {"interbank_loans": 0.0, "loans": 10651288114.81301, "reserves": 494535374.9737184, "bank_notes": 0.0, "open_market_operations": 26617690458.974545, "ach_payee_bank_1": 630746315.2223558}, "liabilities": {"deposits": 24726768748.68592, "receivables": 630746315.2223566, "loans_central_bank": 0.0, "ach_payer_bank_1": 476124342.03964996, "loans_interbank_bank_1": 0.0, "equity": 12560620858.03571}}}, {"bank_2": {"assets": {"interbank_loans": 0.0, "loans": 9899775284.458826, "reserves": 485318077.1282943, "bank_notes": 0.0, "open_market_operations": 27713139839.477516, "ach_payee_bank_2": 571366476.0746571}, "liabilities": {"deposits": 24265903856.414715, "receivables": 571366476.0746571, "loans_central_bank": 0.0, "ach_payer_bank_2": 591910150.4275228, "loans_interbank_bank_2": 0.0, "equity": 13240419194.222393}}}, {"bank_3": {"assets": {"interbank_loans": 0.0, "loans": 9278227951.959894, "reserves": 377638839.9434356, "bank_notes": 0.0, "open_market_operations": 21430235666.76547, "ach_payee_bank_3": 501067113.6638239}, "liabilities": {"deposits": 18881941997.17178, "receivables": 501067113.66382307, "loans_central_bank": 0.0, "ach_payer_bank_3": 502232117.657171, "loans_interbank_bank_3": 0.0, "equity": 11701928343.839851}}}]},{"14": [{"bank_0": {"assets": {"interbank_loans": 0.0, "loans": 11326843638.116323, "reserves": 454838552.75251365, "bank_notes": 0.0, "open_market_operations": 25278975496.511974, "ach_payee_bank_0": 0.0}, "liabilities": {"deposits": 22741927637.625683, "receivables": 5.364418029785156e-07, "loans_central_bank": 0.0, "ach_payer_bank_0": 0.0, "loans_interbank_bank_0": 0.0, "equity": 14318730049.75513}}}, {"bank_1": {"assets": {"interbank_loans": 0.0, "loans": 11294325496.019293, "reserves": 517677805.7382741, "bank_notes": 0.0, "open_market_operations": 27313467415.891766, "ach_payee_bank_1": 0.0}, "liabilities": {"deposits": 25883890286.913704, "receivables": 7.152557373046875e-07, "loans_central_bank": 0.0, "ach_payer_bank_1": 0.0, "loans_interbank_bank_1": 0.0, "equity": 13241580430.735626}}}, {"bank_2": {"assets": {"interbank_loans": 0.0, "loans": 10495316428.969503, "reserves": 510646779.52093774, "bank_notes": 0.0, "open_market_operations": 28468461441.718487, "ach_payee_bank_2": 0.0}, "liabilities": {"deposits": 25532338976.046886, "receivables": -2.384185791015625e-07, "loans_central_bank": 0.0, "ach_payer_bank_2": 0.0, "loans_interbank_bank_2": 0.0, "equity": 13942085674.162037}}}, {"bank_3": {"assets": {"interbank_loans": 0.0, "loans": 9801996822.722239, "reserves": 398093498.67718554, "bank_notes": 0.0, "open_market_operations": 21983502355.42934, "ach_payee_bank_3": 0.0}, "liabilities": {"deposits": 19904674933.859276, "receivables": -1.3113021850585938e-06, "loans_central_bank": 0.0, "ach_payer_bank_3": 0.0, "loans_interbank_bank_3": 0.0, "equity": 12278917742.96949}}}]},{"15": [{"bank_0": {"assets": {"interbank_loans": 0.0, "loans": 12069709148.292694, "reserves": 455404236.5877361, "bank_notes": 0.0, "open_market_operations": 25964363180.11549, "ach_payee_bank_0": 546263004.8450359}, "liabilities": {"deposits": 22770211829.386806, "receivables": 546263004.8450365, "loans_central_bank": 0.0, "ach_payer_bank_0": 667834890.8341258, "loans_interbank_bank_0": 0.0, "equity": 15051429844.77499}}}, {"bank_1": {"assets": {"interbank_loans": 0.0, "loans": 11847909639.572956, "reserves": 515634234.3060518, "bank_notes": 0.0, "open_market_operations": 28056670966.41193, "ach_payee_bank_1": 587387146.7406769}, "liabilities": {"deposits": 25781711715.30259, "receivables": 587387146.7406776, "loans_central_bank": 0.0, "ach_payer_bank_1": 637255200.4887309, "loans_interbank_bank_1": 0.0, "equity": 14001247924.499619}}}, {"bank_2": {"assets": {"interbank_loans": 0.0, "loans": 11053997262.518337, "reserves": 512881372.2324744, "bank_notes": 0.0, "open_market_operations": 29238727973.288715, "ach_payee_bank_2": 647829412.619169}, "liabilities": {"deposits": 25644068611.62372, "receivables": 647829412.6191688, "loans_central_bank": 0.0, "ach_payer_bank_2": 442718393.9805921, "loans_interbank_bank_2": 0.0, "equity": 14718819602.435223}}}, {"bank_3": {"assets": {"interbank_loans": 0.0, "loans": 10370243246.577444, "reserves": 397883072.3919369, "bank_notes": 0.0, "open_market_operations": 22580242394.66845, "ach_payee_bank_3": 506609033.354246}, "liabilities": {"deposits": 19894153619.596844, "receivables": 506609033.3542447, "loans_central_bank": 0.0, "ach_payer_bank_3": 540280112.255679, "loans_interbank_bank_3": 0.0, "equity": 12913934981.785309}}}]},{"16": [{"bank_0": {"assets": {"interbank_loans": 0.0, "loans": 12774801063.98821, "reserves": 479547954.5896955, "bank_notes": 0.0, "open_market_operations": 26485197824.86578, "ach_payee_bank_0": 0.0}, "liabilities": {"deposits": 23977397729.484776, "receivables": 6.556510925292969e-07, "loans_central_bank": 0.0, "ach_payer_bank_0": 0.0, "loans_interbank_bank_0": 0.0, "equity": 15762149113.958912}}}, {"bank_1": {"assets": {"interbank_loans": 0.0, "loans": 12628095904.060686, "reserves": 541617291.8309742, "bank_notes": 0.0, "open_market_operations": 28649620314.205082, "ach_payee_bank_1": 0.0}, "liabilities": {"deposits": 27080864591.54871, "receivables": 6.556510925292969e-07, "loans_central_bank": 0.0, "ach_payer_bank_1": 0.0, "loans_interbank_bank_1": 0.0, "equity": 14738468918.54803}}}, {"bank_2": {"assets": {"interbank_loans": 0.0, "loans": 11643086590.449263, "reserves": 540484777.1960593, "bank_notes": 0.0, "open_market_operations": 30324411818.395866, "ach_payee_bank_2": 0.0}, "liabilities": {"deposits": 27024238859.802967, "receivables": -7.152557373046875e-07, "loans_central_bank": 0.0, "ach_payer_bank_2": 0.0, "loans_interbank_bank_2": 0.0, "equity": 15483744326.238224}}}, {"bank_3": {"assets": {"interbank_loans": 0.0, "loans": 10990874871.948227, "reserves": 416607180.80663675, "bank_notes": 0.0, "open_market_operations": 22949590342.65473, "ach_payee_bank_3": 0.0}, "liabilities": {"deposits": 20830359040.331837, "receivables": -1.4901161193847656e-06, "loans_central_bank": 0.0, "ach_payer_bank_3": 0.0, "loans_interbank_bank_3": 0.0, "equity": 13526713355.077759}}}]},{"17": [{"bank_0": {"assets": {"interbank_loans": 0.0, "loans": 13496701125.873302, "reserves": 480360073.47181827, "bank_notes": 0.0, "open_market_operations": 27203070315.561882, "ach_payee_bank_0": 576310938.839395}, "liabilities": {"deposits": 24018003673.59091, "receivables": 576310938.8393956, "loans_central_bank": 0.0, "ach_payer_bank_0": 613922805.8482119, "loans_interbank_bank_0": 0.0, "equity": 16548205035.467876}}}, {"bank_1": {"assets": {"interbank_loans": 0.0, "loans": 13486259709.933096, "reserves": 543577055.9848397, "bank_notes": 0.0, "open_market_operations": 29425077480.30149, "ach_payee_bank_1": 610061529.3584938}, "liabilities": {"deposits": 27178852799.24198, "receivables": 610061529.3584945, "loans_central_bank": 0.0, "ach_payer_bank_1": 723186126.4357841, "loans_interbank_bank_1": 0.0, "equity": 15552875320.541668}}}, {"bank_2": {"assets": {"interbank_loans": 0.0, "loans": 12324226070.829918, "reserves": 544214694.3121355, "bank_notes": 0.0, "open_market_operations": 31143544853.352264, "ach_payee_bank_2": 622795085.115425}, "liabilities": {"deposits": 27210734715.606773, "receivables": 622795085.1154243, "loans_central_bank": 0.0, "ach_payer_bank_2": 478553374.0919172, "loans_interbank_bank_2": 0.0, "equity": 16322697528.795624}}}, {"bank_3": {"assets": {"interbank_loans": 0.0, "loans": 11712814677.88436, "reserves": 420294461.57572544, "bank_notes": 0.0, "open_market_operations": 23568647792.147984, "ach_payee_bank_3": 487870871.47847104}, "liabilities": {"deposits": 21014723078.78627, "receivables": 487870871.47846955, "loans_central_bank": 0.0, "ach_payer_bank_3": 481376118.4158719, "loans_interbank_bank_3": 0.0, "equity": 14205657734.40593}}}]},{"18": [{"bank_0": {"assets": {"interbank_loans": 0.0, "loans": 14346925996.138348, "reserves": 504792678.91728896, "bank_notes": 0.0, "open_market_operations": 27700047155.828255, "ach_payee_bank_0": 0.0}, "liabilities": {"deposits": 25239633945.86445, "receivables": 7.748603820800781e-07, "loans_central_bank": 0.0, "ach_payer_bank_0": 0.0, "loans_interbank_bank_0": 0.0, "equity": 17312131885.019447}}}, {"bank_1": {"assets": {"interbank_loans": 0.0, "loans": 14148771231.011145, "reserves": 567941120.1218321, "bank_notes": 0.0, "open_market_operations": 30031849176.868206, "ach_payee_bank_1": 0.0}, "liabilities": {"deposits": 28397056006.091606, "receivables": 4.76837158203125e-07, "loans_central_bank": 0.0, "ach_payer_bank_1": 0.0, "loans_interbank_bank_1": 0.0, "equity": 16351505521.909576}}}, {"bank_2": {"assets": {"interbank_loans": 0.0, "loans": 13072760630.727306, "reserves": 573033905.532963, "bank_notes": 0.0, "open_market_operations": 32152539700.86612, "ach_payee_bank_2": 0.0}, "liabilities": {"deposits": 28651695276.64815, "receivables": -1.0132789611816406e-06, "loans_central_bank": 0.0, "ach_payer_bank_2": 0.0, "loans_interbank_bank_2": 0.0, "equity": 17146638960.478237}}}, {"bank_3": {"assets": {"interbank_loans": 0.0, "loans": 12437695597.953789, "reserves": 443602719.2238068, "bank_notes": 0.0, "open_market_operations": 24169970446.87876, "ach_payee_bank_3": 0.0}, "liabilities": {"deposits": 22180135961.19034, "receivables": -1.817941665649414e-06, "loans_central_bank": 0.0, "ach_payer_bank_3": 0.0, "loans_interbank_bank_3": 0.0, "equity": 14871132802.86602}}}]},{"19": [{"bank_0": {"assets": {"interbank_loans": 0.0, "loans": 15152348195.165445, "reserves": 505210304.11277163, "bank_notes": 0.0, "open_market_operations": 28451279478.921776, "ach_payee_bank_0": 613964727.7674669}, "liabilities": {"deposits": 25260515205.63858, "receivables": 613964727.7674677, "loans_central_bank": 0.0, "ach_payer_bank_0": 694082243.7057549, "loans_interbank_bank_0": 0.0, "equity": 18154240528.85566}}}, {"bank_1": {"assets": {"interbank_loans": 0.0, "loans": 14836440264.966063, "reserves": 570231691.7541486, "bank_notes": 0.0, "open_market_operations": 30844482773.192287, "ach_payee_bank_1": 512141868.46195173}, "liabilities": {"deposits": 28511584587.70743, "receivables": 512141868.4619522, "loans_central_bank": 0.0, "ach_payer_bank_1": 514653937.76465493, "loans_interbank_bank_1": 0.0, "equity": 17224916204.44041}}}, {"bank_2": {"assets": {"interbank_loans": 0.0, "loans": 13749643052.477644, "reserves": 575859486.3228589, "bank_notes": 0.0, "open_market_operations": 33022183927.34987, "ach_payee_bank_2": 634991186.3419279}, "liabilities": {"deposits": 28792974316.142944, "receivables": 634991186.3419269, "loans_central_bank": 0.0, "ach_payer_bank_2": 502720303.6058468, "loans_interbank_bank_2": 0.0, "equity": 18051991846.401585}}}, {"bank_3": {"assets": {"interbank_loans": 0.0, "loans": 13210811325.146547, "reserves": 446013482.9932335, "bank_notes": 0.0, "open_market_operations": 24823419831.445602, "ach_payee_bank_3": 527138053.0798588}, "liabilities": {"deposits": 22300674149.661674, "receivables": 527138053.0798569, "loans_central_bank": 0.0, "ach_payer_bank_3": 576779350.5749489, "loans_interbank_bank_3": 0.0, "equity": 15602791139.348759}}}]},{"20": [{"bank_0": {"assets": {"interbank_loans": 0.0, "loans": 15968890992.291077, "reserves": 531995515.53726953, "bank_notes": 0.0, "open_market_operations": 29075534965.065365, "ach_payee_bank_0": 0.0}, "liabilities": {"deposits": 26599775776.863476, "receivables": 6.258487701416016e-07, "loans_central_bank": 0.0, "ach_payer_bank_0": 0.0, "loans_interbank_bank_0": 0.0, "equity": 18976645696.03023}}}, {"bank_1": {"assets": {"interbank_loans": 0.0, "loans": 15663849779.326134, "reserves": 595468117.2469119, "bank_notes": 0.0, "open_market_operations": 31594732516.42389, "ach_payee_bank_1": 0.0}, "liabilities": {"deposits": 29773405862.345592, "receivables": -5.960464477539063e-08, "loans_central_bank": 0.0, "ach_payer_bank_1": 0.0, "loans_interbank_bank_1": 0.0, "equity": 18080644550.65134}}}, {"bank_2": {"assets": {"interbank_loans": 0.0, "loans": 14476823715.533154, "reserves": 606671817.98487, "bank_notes": 0.0, "open_market_operations": 34195502727.06591, "ach_payee_bank_2": 0.0}, "liabilities": {"deposits": 30333590899.2435, "receivables": -7.152557373046875e-07, "loans_central_bank": 0.0, "ach_payer_bank_2": 0.0, "loans_interbank_bank_2": 0.0, "equity": 18945407361.34044}}}, {"bank_3": {"assets": {"interbank_loans": 0.0, "loans": 14064939587.623796, "reserves": 467088004.1227889, "bank_notes": 0.0, "open_market_operations": 25136623567.143715, "ach_payee_bank_3": 0.0}, "liabilities": {"deposits": 23354400206.139446, "receivables": -1.8477439880371094e-06, "loans_central_bank": 0.0, "ach_payer_bank_3": 0.0, "loans_interbank_bank_3": 0.0, "equity": 16314250952.750858}}}]},{"21": [{"bank_0": {"assets": {"interbank_loans": 0.0, "loans": 16811884900.497953, "reserves": 535133298.2545975, "bank_notes": 0.0, "open_market_operations": 29861371447.627163, "ach_payee_bank_0": 557090760.556865}, "liabilities": {"deposits": 26756664912.729874, "receivables": 557090760.5568657, "loans_central_bank": 0.0, "ach_payer_bank_0": 572334048.6426638, "loans_interbank_bank_0": 0.0, "equity": 19879390685.007175}}}, {"bank_1": {"assets": {"interbank_loans": 0.0, "loans": 16388211659.031935, "reserves": 595614300.2654754, "bank_notes": 0.0, "open_market_operations": 32451919858.094955, "ach_payee_bank_1": 651657399.029557}, "liabilities": {"deposits": 29780715013.27377, "receivables": 651657399.0295569, "loans_central_bank": 0.0, "ach_payer_bank_1": 637717899.3362697, "loans_interbank_bank_1": 0.0, "equity": 19017312904.782326}}}, {"bank_2": {"assets": {"interbank_loans": 0.0, "loans": 15280386558.225058, "reserves": 609824997.7626969, "bank_notes": 0.0, "open_market_operations": 35120255832.49841, "ach_payee_bank_2": 704492434.579632}, "liabilities": {"deposits": 30491249888.134842, "receivables": 704492434.5796313, "loans_central_bank": 0.0, "ach_payer_bank_2": 597261286.7706342, "loans_interbank_bank_2": 0.0, "equity": 19921956213.580696}}}, {"bank_3": {"assets": {"interbank_loans": 0.0, "loans": 14905000495.567345, "reserves": 469832834.64753795, "bank_notes": 0.0, "open_market_operations": 25815969337.335808, "ach_payee_bank_3": 496038321.138215}, "liabilities": {"deposits": 23491641732.376896, "receivables": 496038321.13821316, "loans_central_bank": 0.0, "ach_payer_bank_3": 601965680.5547009, "loans_interbank_bank_3": 0.0, "equity": 17097195254.619095}}}]},{"22": [{"bank_0": {"assets": {"interbank_loans": 0.0, "loans": 17659402323.441536, "reserves": 562104382.756092, "bank_notes": 0.0, "open_market_operations": 30653707907.524303, "ach_payee_bank_0": 0.0}, "liabilities": {"deposits": 28105219137.8046, "receivables": 2.980232238769531e-07, "loans_central_bank": 0.0, "ach_payer_bank_0": 0.0, "loans_interbank_bank_0": 0.0, "equity": 20769995475.91733}}}, {"bank_1": {"assets": {"interbank_loans": 0.0, "loans": 17233042020.312244, "reserves": 622465915.2060645, "bank_notes": 0.0, "open_market_operations": 33198632277.77742, "ach_payee_bank_1": 0.0}, "liabilities": {"deposits": 31123295760.303223, "receivables": 4.76837158203125e-07, "loans_central_bank": 0.0, "ach_payer_bank_1": 0.0, "loans_interbank_bank_1": 0.0, "equity": 19930844452.992508}}}, {"bank_2": {"assets": {"interbank_loans": 0.0, "loans": 16158896604.702194, "reserves": 641308565.7072513, "bank_notes": 0.0, "open_market_operations": 36147494296.46192, "ach_payee_bank_2": 0.0}, "liabilities": {"deposits": 32065428285.362564, "receivables": -2.384185791015625e-07, "loans_central_bank": 0.0, "ach_payer_bank_2": 0.0, "loans_interbank_bank_2": 0.0, "equity": 20882271181.508804}}}, {"bank_3": {"assets": {"interbank_loans": 0.0, "loans": 15669168188.340271, "reserves": 491246163.8274915, "bank_notes": 0.0, "open_market_operations": 26264778663.38028, "ach_payee_bank_3": 0.0}, "liabilities": {"deposits": 24562308191.374577, "receivables": -1.8477439880371094e-06, "loans_central_bank": 0.0, "ach_payer_bank_3": 0.0, "loans_interbank_bank_3": 0.0, "equity": 17862884824.173466}}}]},{"23": [{"bank_0": {"assets": {"interbank_loans": 0.0, "loans": 18575301701.192287, "reserves": 564970318.4163343, "bank_notes": 0.0, "open_market_operations": 31482640482.312046, "ach_payee_bank_0": 542672280.1665281}, "liabilities": {"deposits": 28248515920.816715, "receivables": 542672280.1665283, "loans_central_bank": 0.0, "ach_payer_bank_0": 635304202.5981811, "loans_interbank_bank_0": 0.0, "equity": 21739092378.50577}}}, {"bank_1": {"assets": {"interbank_loans": 0.0, "loans": 18055164320.20349, "reserves": 624987736.1201335, "bank_notes": 0.0, "open_market_operations": 34096966332.46811, "ach_payee_bank_1": 636229944.8902731}, "liabilities": {"deposits": 31249386806.006676, "receivables": 636229944.8902736, "loans_central_bank": 0.0, "ach_payer_bank_1": 594440839.3418031, "loans_interbank_bank_1": 0.0, "equity": 20933290743.443253}}}, {"bank_2": {"assets": {"interbank_loans": 0.0, "loans": 16981235956.242504, "reserves": 646370295.7201326, "bank_notes": 0.0, "open_market_operations": 37123306789.00416, "ach_payee_bank_2": 646288661.1921043}, "liabilities": {"deposits": 32318514786.006626, "receivables": 646288661.1921041, "loans_central_bank": 0.0, "ach_payer_bank_2": 499249766.74284196, "loans_interbank_bank_2": 0.0, "equity": 21933148488.21733}}}, {"bank_3": {"assets": {"interbank_loans": 0.0, "loans": 16539631815.047146, "reserves": 494939247.77880967, "bank_notes": 0.0, "open_market_operations": 26973789042.101524, "ach_payee_bank_3": 464498871.01007897}, "liabilities": {"deposits": 24746962388.940483, "receivables": 464498871.0100771, "loans_central_bank": 0.0, "ach_payer_bank_3": 560694948.576158, "loans_interbank_bank_3": 0.0, "equity": 18700702767.410843}}}]},{"24": [{"bank_0": {"assets": {"interbank_loans": 0.0, "loans": 19554963051.724926, "reserves": 589060837.2716706, "bank_notes": 0.0, "open_market_operations": 32007005840.72838, "ach_payee_bank_0": 0.0}, "liabilities": {"deposits": 29453041863.58353, "receivables": 0.0, "loans_central_bank": 0.0, "ach_payer_bank_0": 0.0, "loans_interbank_bank_0": 0.0, "equity": 22697987866.141445}}}, {"bank_1": {"assets": {"interbank_loans": 0.0, "loans": 18992149440.462696, "reserves": 654772774.5838468, "bank_notes": 0.0, "open_market_operations": 35017249201.24618, "ach_payee_bank_1": 0.0}, "liabilities": {"deposits": 32738638729.19234, "receivables": 5.364418029785156e-07, "loans_central_bank": 0.0, "ach_payer_bank_1": 0.0, "loans_interbank_bank_1": 0.0, "equity": 21925532687.100384}}}, {"bank_2": {"assets": {"interbank_loans": 0.0, "loans": 17815058229.966324, "reserves": 676872817.3510824, "bank_notes": 0.0, "open_market_operations": 38321392205.36588, "ach_payee_bank_2": 0.0}, "liabilities": {"deposits": 33843640867.55412, "receivables": 5.960464477539063e-08, "loans_central_bank": 0.0, "ach_payer_bank_2": 0.0, "loans_interbank_bank_2": 0.0, "equity": 22969682385.12917}}}, {"bank_3": {"assets": {"interbank_loans": 0.0, "loans": 17482188299.426456, "reserves": 520168849.0573156, "bank_notes": 0.0, "open_market_operations": 27529334483.601562, "ach_payee_bank_3": 0.0}, "liabilities": {"deposits": 26008442452.86578, "receivables": -1.6689300537109375e-06, "loans_central_bank": 0.0, "ach_payer_bank_3": 0.0, "loans_interbank_bank_3": 0.0, "equity": 19523249179.219555}}}]},{"25": [{"bank_0": {"assets": {"interbank_loans": 0.0, "loans": 20358491986.02574, "reserves": 362080315.95621896, "bank_notes": 0.0, "open_market_operations": 33102507059.85093, "ach_payee_bank_0": 12090965825.287296}, "liabilities": {"deposits": 18104015797.810947, "receivables": 12090965825.287296, "loans_central_bank": 0.0, "ach_payer_bank_0": 11985893845.869072, "loans_interbank_bank_0": 0.0, "equity": 23733169718.152863}}}, {"bank_1": {"assets": {"interbank_loans": 0.0, "loans": 19797980936.619915, "reserves": 437541835.3496091, "bank_notes": 0.0, "open_market_operations": 36184684788.265724, "ach_payee_bank_1": 12169243244.219347}, "liabilities": {"deposits": 21877091767.480453, "receivables": 12169243244.219347, "loans_central_bank": 0.0, "ach_payer_bank_1": 11541733431.422958, "loans_interbank_bank_1": 0.0, "equity": 23001382361.331833}}}, {"bank_2": {"assets": {"interbank_loans": 0.0, "loans": 18625207816.880955, "reserves": 411852139.1510969, "bank_notes": 0.0, "open_market_operations": 39626276545.43929, "ach_payee_bank_2": 10285622650.076286}, "liabilities": {"deposits": 20592606957.554848, "receivables": 10285622650.076286, "loans_central_bank": 0.0, "ach_payer_bank_2": 13970789094.628485, "loans_interbank_bank_2": 0.0, "equity": 24099940449.288017}}}, {"bank_3": {"assets": {"interbank_loans": 0.0, "loans": 18218938010.171413, "reserves": 281537812.4684206, "bank_notes": 0.0, "open_market_operations": 28514983123.612705, "ach_payee_bank_3": 15469063308.201635}, "liabilities": {"deposits": 14076890623.421032, "receivables": 15469063308.201633, "loans_central_bank": 0.0, "ach_payer_bank_3": 12516478655.864046, "loans_interbank_bank_3": 0.0, "equity": 20422089666.96747}}}]},{"26": [{"bank_0": {"assets": {"interbank_loans": 0.0, "loans": 18826946571.232777, "reserves": 566133876.6138937, "bank_notes": 0.0, "open_market_operations": 33767461795.968933, "ach_payee_bank_0": 0.0}, "liabilities": {"deposits": 28306693830.694687, "receivables": -8.344650268554688e-06, "loans_central_bank": 0.0, "ach_payer_bank_0": 0.0, "loans_interbank_bank_0": 0.0, "equity": 24853848413.120926}}}, {"bank_1": {"assets": {"interbank_loans": 0.0, "loans": 19214453287.805122, "reserves": 665433934.5397462, "bank_notes": 0.0, "open_market_operations": 37554601982.96232, "ach_payee_bank_1": 0.0}, "liabilities": {"deposits": 33271696726.98731, "receivables": 7.68899917602539e-06, "loans_central_bank": 0.0, "ach_payer_bank_1": 0.0, "loans_interbank_bank_1": 0.0, "equity": 24162792478.319874}}}, {"bank_2": {"assets": {"interbank_loans": 0.0, "loans": 17786956706.888283, "reserves": 595528748.6694179, "bank_notes": 0.0, "open_market_operations": 38970028750.72046, "ach_payee_bank_2": 0.0}, "liabilities": {"deposits": 29776437433.470894, "receivables": -9.834766387939453e-06, "loans_central_bank": 0.0, "ach_payer_bank_2": 0.0, "loans_interbank_bank_2": 2244888901.402225, "equity": 25331187871.405052}}}, {"bank_3": {"assets": {"interbank_loans": 2244888901.402225, "loans": 16669083184.58147, "reserves": 555782255.3787241, "bank_notes": 0.0, "open_market_operations": 29729725286.976303, "ach_payee_bank_3": 0.0}, "liabilities": {"deposits": 27789112768.936203, "receivables": -1.099705696105957e-05, "loans_central_bank": 0.0, "ach_payer_bank_3": 0.0, "loans_interbank_bank_3": 0.0, "equity": 21410366859.40253}}}]},{"27": [{"bank_0": {"assets": {"interbank_loans": 122348062.1611864, "loans": 13359150192.010853, "reserves": 443785814.45270735, "bank_notes": 0.0, "open_market_operations": 34683753048.83241, "ach_payee_bank_0": 490948745.8795321}, "liabilities": {"deposits": 22189290722.63537, "receivables": 490948745.87952375, "loans_central_bank": 0.0, "ach_payer_bank_0": 488713558.65438604, "loans_interbank_bank_0": 0.0, "equity": 25931032836.167416}}}, {"bank_1": {"assets": {"interbank_loans": 108175244.12034953, "loans": 14583003694.036577, "reserves": 557258690.4193966, "bank_notes": 0.0, "open_market_operations": 38573658538.343285, "ach_payee_bank_1": 638767826.745822}, "liabilities": {"deposits": 27862934520.96983, "receivables": 638767826.7458298, "loans_central_bank": 0.0, "ach_payer_bank_1": 651510029.1596509, "loans_interbank_bank_1": 0.0, "equity": 25307651616.790115}}}, {"bank_2": {"assets": {"interbank_loans": 0.0, "loans": 12954688926.036268, "reserves": 484726209.7265525, "bank_notes": 0.0, "open_market_operations": 40018176940.73576, "ach_payee_bank_2": 576081621.8283561}, "liabilities": {"deposits": 24236310486.327625, "receivables": 576081621.8283464, "loans_central_bank": 0.0, "ach_payer_bank_2": 582434815.837739, "loans_interbank_bank_2": 2124769923.2443388, "equity": 26514076851.088886}}}, {"bank_3": {"assets": {"interbank_loans": 1894246616.962803, "loans": 10869655965.717308, "reserves": 427985488.93478537, "bank_notes": 0.0, "open_market_operations": 31014890274.060852, "ach_payee_bank_3": 488713683.54997694}, "liabilities": {"deposits": 21399274446.73927, "receivables": 488713683.549966, "loans_central_bank": 0.0, "ach_payer_bank_3": 471853474.351911, "loans_interbank_bank_3": 0.0, "equity": 22335650424.584587}}}]},{"28": [{"bank_0": {"assets": {"interbank_loans": 0.0, "loans": 13953791344.064144, "reserves": 461944290.25073135, "bank_notes": 0.0, "open_market_operations": 35624908168.134735, "ach_payee_bank_0": 0.0}, "liabilities": {"deposits": 23097214512.536568, "receivables": -7.62939453125e-06, "loans_central_bank": 0.0, "ach_payer_bank_0": 0.0, "loans_interbank_bank_0": 24975119.955279708, "equity": 26918454169.957767}}}, {"bank_1": {"assets": {"interbank_loans": 0.0, "loans": 15238413391.376507, "reserves": 579905950.0084946, "bank_notes": 0.0, "open_market_operations": 39548870989.4188, "ach_payee_bank_1": 0.0}, "liabilities": {"deposits": 28995297500.42473, "receivables": 7.867813110351562e-06, "loans_central_bank": 0.0, "ach_payer_bank_1": 0.0, "loans_interbank_bank_1": 0.0, "equity": 26371892830.379066}}}, {"bank_2": {"assets": {"interbank_loans": 0.0, "loans": 13479778545.992157, "reserves": 510893841.3351865, "bank_notes": 0.0, "open_market_operations": 40326422737.12884, "ach_payee_bank_2": 0.0}, "liabilities": {"deposits": 25544692066.759327, "receivables": -1.0073184967041016e-05, "loans_central_bank": 0.0, "ach_payer_bank_2": 0.0, "loans_interbank_bank_2": 1150076583.0448213, "equity": 27622326474.65204}}}, {"bank_3": {"assets": {"interbank_loans": 1175051703.000101, "loans": 11333452910.8631, "reserves": 443962647.56061745, "bank_notes": 0.0, "open_market_operations": 32427162811.108284, "ach_payee_bank_3": 0.0}, "liabilities": {"deposits": 22198132378.030865, "receivables": -1.1116266250610352e-05, "loans_central_bank": 0.0, "ach_payer_bank_3": 0.0, "loans_interbank_bank_3": 0.0, "equity": 23181497694.50125}}}]},{"29": [{"bank_0": {"assets": {"interbank_loans": 0.0, "loans": 14696189708.391264, "reserves": 461097088.5172051, "bank_notes": 0.0, "open_market_operations": 36567473924.899956, "ach_payee_bank_0": 527261940.15055186}, "liabilities": {"deposits": 23054854425.860256, "receivables": 527261940.1505442, "loans_central_bank": 0.0, "ach_payer_bank_0": 684065322.332734, "loans_interbank_bank_0": 0.0, "equity": 27985840973.615444}}}, {"bank_1": {"assets": {"interbank_loans": 1737305.5891034603, "loans": 15881905718.198278, "reserves": 578168644.4193912, "bank_notes": 0.0, "open_market_operations": 40622042694.39299, "ach_payee_bank_1": 617574598.5898509}, "liabilities": {"deposits": 28908432220.96956, "receivables": 617574598.5898588, "loans_central_bank": 0.0, "ach_payer_bank_1": 653445240.5882342, "loans_interbank_bank_1": 0.0, "equity": 27521976901.04196}}}, {"bank_2": {"assets": {"interbank_loans": 0.0, "loans": 13956360452.549677, "reserves": 509126198.514035, "bank_notes": 0.0, "open_market_operations": 40953378116.052956, "ach_payee_bank_2": 675792766.2080901}, "liabilities": {"deposits": 25456309925.701748, "receivables": 675792766.2080799, "loans_central_bank": 0.0, "ach_payer_bank_2": 496013876.99942505, "loans_interbank_bank_2": 680993490.1298763, "equity": 28785547474.285633}}}, {"bank_3": {"assets": {"interbank_loans": 679256184.5407728, "loans": 11781971476.015879, "reserves": 442128146.5258298, "bank_notes": 0.0, "open_market_operations": 33804714626.87271, "ach_payee_bank_3": 501483561.20237}, "liabilities": {"deposits": 22106407326.291485, "receivables": 501483561.2023589, "loans_central_bank": 0.0, "ach_payer_bank_3": 488588426.2304701, "loans_interbank_bank_3": 0.0, "equity": 24113074681.43325}}}]},{"30": [{"bank_0": {"assets": {"interbank_loans": 0.0, "loans": 15499047375.9501, "reserves": 483019976.2513951, "bank_notes": 0.0, "open_market_operations": 37208699557.11704, "ach_payee_bank_0": 0.0}, "liabilities": {"deposits": 24150998812.569756, "receivables": -7.659196853637695e-06, "loans_central_bank": 0.0, "ach_payer_bank_0": 0.0, "loans_interbank_bank_0": 0.0, "equity": 29039768096.748787}}}, {"bank_1": {"assets": {"interbank_loans": 0.0, "loans": 16514894341.726704, "reserves": 603241173.9136305, "bank_notes": 0.0, "open_market_operations": 41724335268.80148, "ach_payee_bank_1": 0.0}, "liabilities": {"deposits": 30162058695.681526, "receivables": 7.271766662597656e-06, "loans_central_bank": 0.0, "ach_payer_bank_1": 0.0, "loans_interbank_bank_1": 13491772.881283045, "equity": 28666920315.879}}}, {"bank_2": {"assets": {"interbank_loans": 0.0, "loans": 14494873544.28681, "reserves": 532264660.6351756, "bank_notes": 0.0, "open_market_operations": 41514002241.69301, "ach_payee_bank_2": 0.0}, "liabilities": {"deposits": 26613233031.75878, "receivables": -9.775161743164062e-06, "loans_central_bank": 0.0, "ach_payer_bank_2": 0.0, "loans_interbank_bank_2": 0.0, "equity": 29927907414.85622}}}, {"bank_3": {"assets": {"interbank_loans": 13491772.881283045, "loans": 12280406451.985432, "reserves": 460870039.25458527, "bank_notes": 0.0, "open_market_operations": 35336978389.23122, "ach_payee_bank_3": 0.0}, "liabilities": {"deposits": 23043501962.72926, "receivables": -1.0788440704345703e-05, "loans_central_bank": 0.0, "ach_payer_bank_3": 0.0, "loans_interbank_bank_3": 0.0, "equity": 25048244690.62327}}}]}]