[{"0": [{"central_bank": {"assets": {"loans_central_bank": 0.0}, "liabilities": {"reserves": 1516015587.2400017, "bank_notes": 0.0, "open_market_operations": 74284763851.76001}}}]},{"1": [{"central_bank": {"assets": {"loans_central_bank": 0.0}, "liabilities": {"reserves": 1529300222.620837, "bank_notes": 0.0, "open_market_operations": 76287220871.7535}}}]},{"2": [{"central_bank": {"assets": {"loans_central_bank": 0.0}, "liabilities": {"reserves": 1543358623.7152963, "bank_notes": 0.0, "open_market_operations": 78343241460.0842}}}]},{"3": [{"central_bank": {"assets": {"loans_central_bank": 0.0}, "liabilities": {"reserves": 1558900998.5205746, "bank_notes": 0.0, "open_market_operations": 80453568873.91121}}}]},{"4": [{"central_bank": {"assets": {"loans_central_bank": 0.0}, "liabilities": {"reserves": 1575409654.7087197, "bank_notes": 0.0, "open_market_operations": 82620194439.24792}}}]},{"5": [{"central_bank": {"assets": {"loans_central_bank": 0.0}, "liabilities": {"reserves": 1595478026.9516828, "bank_notes": 0.0, "open_market_operations": 84842052390.39833}}}]},{"6": [{"central_bank": {"assets": {"loans_central_bank": 0.0}, "liabilities": {"reserves": 1618735654.026045, "bank_notes": 0.0, "open_market_operations": 87121011937.65678}}}]},{"7": [{"central_bank": {"assets": {"loans_central_bank": 0.0}, "liabilities": {"reserves": 1649147199.4871135, "bank_notes": 0.0, "open_market_operations": 89454657888.17902}}}]},{"8": [{"central_bank": {"assets": {"loans_central_bank": 0.0}, "liabilities": {"reserves": 1680505471.1402876, "bank_notes": 0.0, "open_market_operations": 91850681367.81334}}}]},{"9": [{"central_bank": {"assets": {"loans_central_bank": 0.0}, "liabilities": {"reserves": 1711507057.4831958, "bank_notes": 0.0, "open_market_operations": 94312078422.96155}}}]},{"10": [{"central_bank": {"assets": {"loans_central_bank": 0.0}, "liabilities": {"reserves": 1747732550.1651154, "bank_notes": 0.0, "open_market_operations": 96835042395.58464}}}]},{"11": [{"central_bank": {"assets": {"loans_central_bank": 0.0}, "liabilities": {"reserves": 1788220310.0070522, "bank_notes": 0.0, "open_market_operations": 99422205563.54593}}}]},{"12": [{"central_bank": {"assets": {"loans_central_bank": 0.0}, "liabilities": {"reserves": 1831878708.8126562, "bank_notes": 0.0, "open_market_operations": 102076401621.45718}}}]},{"13": [{"central_bank": {"assets": {"loans_central_bank": 0.0}, "liabilities": {"reserves": 1877606440.5491054, "bank_notes": 0.0, "open_market_operations": 104800550835.0079}}}]},{"14": [{"central_bank": {"assets": {"loans_central_bank": 0.0}, "liabilities": {"reserves": 1924437630.32346, "bank_notes": 0.0, "open_market_operations": 107597517281.12384}}}]},{"15": [{"central_bank": {"assets": {"loans_central_bank": 0.0}, "liabilities": {"reserves": 1976705789.203599, "bank_notes": 0.0, "open_market_operations": 110464943368.44524}}}]},{"16": [{"central_bank": {"assets": {"loans_central_bank": 0.0}, "liabilities": {"reserves": 2033304202.9930573, "bank_notes": 0.0, "open_market_operations": 113405847756.85478}}}]},{"17": [{"central_bank": {"assets": {"loans_central_bank": 0.0}, "liabilities": {"reserves": 2090819145.1547441, "bank_notes": 0.0, "open_market_operations": 116425638030.91092}}}]},{"18": [{"central_bank": {"assets": {"loans_central_bank": 0.0}, "liabilities": {"reserves": 2147582698.0221653, "bank_notes": 0.0, "open_market_operations": 119528122702.89848}}}]},{"19": [{"central_bank": {"assets": {"loans_central_bank": 0.0}, "liabilities": {"reserves": 2207660995.5864162, "bank_notes": 0.0, "open_market_operations": 122711479578.68597}}}]},{"20": [{"central_bank": {"assets": {"loans_central_bank": 0.0}, "liabilities": {"reserves": 2269912700.8537807, "bank_notes": 0.0, "open_market_operations": 125979044489.28598}}}]},{"21": [{"central_bank": {"assets": {"loans_central_bank": 0.0}, "liabilities": {"reserves": 2335376452.872173, "bank_notes": 0.0, "open_market_operations": 129332063808.54813}}}]},{"22": [{"central_bank": {"assets": {"loans_central_bank": 0.0}, "liabilities": {"reserves": 2400726467.982467, "bank_notes": 0.0, "open_market_operations": 132776182153.79597}}}]},{"23": [{"central_bank": {"assets": {"loans_central_bank": 0.0}, "liabilities": {"reserves": 2468069982.8432913, "bank_notes": 0.0, "open_market_operations": 136311764290.5946}}}]},{"24": [{"central_bank": {"assets": {"loans_central_bank": 0.0}, "liabilities": {"reserves": 2540021520.554364, "bank_notes": 0.0, "open_market_operations": 139938677596.1028}}}]},{"25": [{"central_bank": {"assets": {"loans_central_bank": 0.0}, "liabilities": {"reserves": 2562279378.6160135, "bank_notes": 0.0, "open_market_operations": 143713702074.3138}}}]},{"26": [{"central_bank": {"assets": {"loans_central_bank": 0.0}, "liabilities": {"reserves": 1933943455.6992984, "bank_notes": 0.0, "open_market_operations": 148241756872.2522}}}]},{"27": [{"central_bank": {"assets": {"loans_central_bank": 0.0}, "liabilities": {"reserves": 1968288014.872776, "bank_notes": 0.0, "open_market_operations": 152230001453.82898}}}]},{"28": [{"central_bank": {"assets": {"loans_central_bank": 0.0}, "liabilities": {"reserves": 2006099371.0523386, "bank_notes": 0.0, "open_market_operations": 156323001575.2295}}}]},{"29": [{"central_bank": {"assets": {"loans_central_bank": 0.0}, "liabilities": {"reserves": 2047636060.715838, "bank_notes": 0.0, "open_market_operations": 160523341276.22342}}}]},{"30": [{"central_bank": {"assets": {"loans_central_bank": 0.0}, "liabilities": {"reserves": 2088787503.959322, "bank_notes": 0.0, "open_market_operations": 164838043831.73608}}}]}]