[{"0": [{"central_bank": {"assets": {"loans_central_bank": 0.0}, "liabilities": {"reserves": 1813606687.3999977, "bank_notes": 0.0, "open_market_operations": 88866727750.6}}}]},{"1": [{"central_bank": {"assets": {"loans_central_bank": 0.0}, "liabilities": {"reserves": 1775199548.6410651, "bank_notes": 0.0, "open_market_operations": 91316562961.75836}}}]},{"2": [{"central_bank": {"assets": {"loans_central_bank": 0.0}, "liabilities": {"reserves": 1849238002.410079, "bank_notes": 0.0, "open_market_operations": 93523496195.73898}}}]},{"3": [{"central_bank": {"assets": {"loans_central_bank": 0.0}, "liabilities": {"reserves": 1810948168.8740592, "bank_notes": 0.0, "open_market_operations": 96099577054.82365}}}]},{"4": [{"central_bank": {"assets": {"loans_central_bank": 0.0}, "liabilities": {"reserves": 1901541534.8397284, "bank_notes": 0.0, "open_market_operations": 98405277370.20059}}}]},{"5": [{"central_bank": {"assets": {"loans_central_bank": 0.0}, "liabilities": {"reserves": 1873284460.710967, "bank_notes": 0.0, "open_market_operations": 101103794217.91656}}}]},{"6": [{"central_bank": {"assets": {"loans_central_bank": 0.0}, "liabilities": {"reserves": 1962333928.4522123, "bank_notes": 0.0, "open_market_operations": 103564562866.63438}}}]},{"7": [{"central_bank": {"assets": {"loans_central_bank": 0.0}, "liabilities": {"reserves": 1945029672.2982109, "bank_notes": 0.0, "open_market_operations": 106392125816.04482}}}]},{"8": [{"central_bank": {"assets": {"loans_central_bank": 0.0}, "liabilities": {"reserves": 2045972791.117494, "bank_notes": 0.0, "open_market_operations": 108964901428.03752}}}]},{"9": [{"central_bank": {"assets": {"loans_central_bank": 0.0}, "liabilities": {"reserves": 2034861901.9088078, "bank_notes": 0.0, "open_market_operations": 111932810984.8784}}}]},{"10": [{"central_bank": {"assets": {"loans_central_bank": 0.0}, "liabilities": {"reserves": 2145346103.0881996, "bank_notes": 0.0, "open_market_operations": 114651527177.53412}}}]},{"11": [{"central_bank": {"assets": {"loans_central_bank": 0.0}, "liabilities": {"reserves": 2140254595.3078706, "bank_notes": 0.0, "open_market_operations": 117767725824.93233}}}]},{"12": [{"central_bank": {"assets": {"loans_central_bank": 0.0}, "liabilities": {"reserves": 2260479400.8092012, "bank_notes": 0.0, "open_market_operations": 120644367098.80782}}}]},{"13": [{"central_bank": {"assets": {"loans_central_bank": 0.0}, "liabilities": {"reserves": 2267429570.565016, "bank_notes": 0.0, "open_market_operations": 123911141763.56366}}}]},{"14": [{"central_bank": {"assets": {"loans_central_bank": 0.0}, "liabilities": {"reserves": 2395589922.6791067, "bank_notes": 0.0, "open_market_operations": 126946551115.79176}}}]},{"15": [{"central_bank": {"assets": {"loans_central_bank": 0.0}, "liabilities": {"reserves": 2418339079.286611, "bank_notes": 0.0, "open_market_operations": 130368538643.01959}}}]},{"16": [{"central_bank": {"assets": {"loans_central_bank": 0.0}, "liabilities": {"reserves": 2544162533.7817526, "bank_notes": 0.0, "open_market_operations": 133585241830.58911}}}]},{"17": [{"central_bank": {"assets": {"loans_central_bank": 0.0}, "liabilities": {"reserves": 2557951382.6546774, "bank_notes": 0.0, "open_market_operations": 137196332735.5042}}}]},{"18": [{"central_bank": {"assets": {"loans_central_bank": 0.0}, "liabilities": {"reserves": 2700117291.5385647, "bank_notes": 0.0, "open_market_operations": 140565167909.38458}}}]},{"19": [{"central_bank": {"assets": {"loans_central_bank": 0.0}, "liabilities": {"reserves": 2725582394.8526225, "bank_notes": 0.0, "open_market_operations": 144353985164.36227}}}]},{"20": [{"central_bank": {"assets": {"loans_central_bank": 0.0}, "liabilities": {"reserves": 2868243440.642989, "bank_notes": 0.0, "open_market_operations": 147924483808.17584}}}]},{"21": [{"central_bank": {"assets": {"loans_central_bank": 0.0}, "liabilities": {"reserves": 2899183948.3003974, "bank_notes": 0.0, "open_market_operations": 151907523131.6575}}}]},{"22": [{"central_bank": {"assets": {"loans_central_bank": 0.0}, "liabilities": {"reserves": 3042152268.3758802, "bank_notes": 0.0, "open_market_operations": 155693415595.14963}}}]},{"23": [{"central_bank": {"assets": {"loans_central_bank": 0.0}, "liabilities": {"reserves": 3070831614.329987, "bank_notes": 0.0, "open_market_operations": 159889528615.89062}}}]},{"24": [{"central_bank": {"assets": {"loans_central_bank": 0.0}, "liabilities": {"reserves": 3220968446.4099693, "bank_notes": 0.0, "open_market_operations": 163885313595.23666}}}]},{"25": [{"central_bank": {"assets": {"loans_central_bank": 0.0}, "liabilities": {"reserves": 1931281765.802875, "bank_notes": 0.0, "open_market_operations": 169622082506.2892}}}]},{"26": [{"central_bank": {"assets": {"loans_central_bank": 0.0}, "liabilities": {"reserves": 3130908218.497879, "bank_notes": 0.0, "open_market_operations": 172784873902.3118}}}]},{"27": [{"central_bank": {"assets": {"loans_central_bank": 0.0}, "liabilities": {"reserves": 2377407949.6917505, "bank_notes": 0.0, "open_market_operations": 178226948916.25034}}}]},{"28": [{"central_bank": {"assets": {"loans_central_bank": 0.0}, "liabilities": {"reserves": 2492867819.589614, "bank_notes": 0.0, "open_market_operations": 182757336162.31528}}}]},{"29": [{"central_bank": {"assets": {"loans_central_bank": 0.0}, "liabilities": {"reserves": 2485963003.402245, "bank_notes": 0.0, "open_market_operations": 187723421787.94507}}}]},{"30": [{"central_bank": {"assets": {"loans_central_bank": 0.0}, "liabilities": {"reserves": 2600261303.527322, "bank_notes": 0.0, "open_market_operations": 192506593867.4887}}}]}]